Workbook

Sheet RC GP
AN1: Accumulated | AP1: Ordinary Dep
AD4: in years | AE4: in Months | AH4: in years | AI4: in days
A5: Company Code | B5: External/Legacy Asset Number* External/legacy asset ID. It is an unique number that identifies a fixed asset in the Legacy System. Please note: In S/4HANA Cloud only INTERNAL number assignment is supported. The legacy asset number is migrated to the field "Original Asset" in the tab "Origin" for reference. Key fields are mandatory and must always be filled with a unique key. If there is internal numbering, you can provide the key of your source system or any other unique key. The key is technically mandatory for the tool to internally connect the records of subordinated sheets with the records of the superordinated sheets. Type: Text Length: 12 | C5: Asset number | D5: Main Asset Legacy Number | E5: Asset Subnumber* Must be "0", when migrating a MAIN asset source file. Must be a sequential number (unequal "0"), when migrating an asset subnumber source file (max. 4-digits). The asset subnumber is migrated to the field "Original Asset Subnumber" in the tab "Origin" for reference. This is the number which, together with the main asset number, uniquely identifies a fixed asset in Asset Accounting. Using the asset sub-number, you can: - Provide for separate management of later acquisitions to assets. - Represent complex fixed assets with their component parts. Type: Text Length: 4 | F5: Asset Class* Note: Ensure that the subasset has the same asset class than the main asset. Type: Text Length: 80 | G5: Asset Class in SAP | I5: PM Sheet Maped Cost Center | J5: Cost Center Code | K5: Equipment ID | L5: Asset Description* Asset Description Type: Text Length: 50 | M5: Asset Description 2 Additional Asset description. Type: Text Length: 50 | N5: Serial Number You can enter the manufacturer's serial number in this field. Type: Text Length: 18 | O5: Quantity Quantity Type: Number Length: 13 Decimal: 3 | P5: Base Unit of Measure Base Unit of Measure, for example: KG, KM, TON... Type: Text Length: 80 | Q5: Asset is managed historically Set this indicator to 'X', if the asset is managed historically. Type: Text Length: 1 | R5: Asset Main Number Text In this field, you can enter any desired name for an asset main number. The text is then used, for example, in reporting, and in the display values transaction when accessing totals per asset main number. Type: Text Length: 50 | S5: Original Purchase Date | T5: Asset Capitalization Date* Reference date of the posting that leads to asset being capitalized. Type: Date | U5: Deactivation Date Asset value date of the retirement posting for a full retirement in this field. Type: Date | V5: Plant The Plant is mandatory for migrating an Asset Location. Without indicating the Plant the Asset Location cannot be determined. Type: Text Length: 80 | W5: Asset Location Migrating an Asset Location, the indication of the Plant is mandatory. Without a plant the Asset Location cannot be determined. Type: Text Length: 80 | X5: License Plate No. of Vehicle You can enter the license plate number for a vehicle here. Your entry is saved as time-dependent data, so that a history is created when there is a change in the license plate number. Type: Text Length: 15 | Y5: Fiscal Year of Original Acquisition Fiscal year in which the asset was originally acquired (before the asset transfer). This field is not automatically filled; you need to supply it. Type: Number Length: 4 | Z5: Original Acquisition Value Acquisition value of the asset before the asset transfer. This field is not automatically filled; you need to supply it. Type: Number Length: 23 Decimal: 2 | AA5: Depreciation Area* Depreciation area, which is managed in the system as a real depreciation area (not a derived depreciation area). Type: Text Length: 80 | AB5: Depreciation Key* Depreciation keys are defined at the level of the chart of depreciation. Type: Text Length: 80 | AC5: Life of Assets as per Co's Act | AD5: Useful Life (in years) The two fields ‘Useful Life (in years)’ and ‘Useful Life (in periods)’ are additive. For example, a useful life of 3.5 years would be maintained as ‘Useful Life (in years)’ = 3 and ‘Useful Life (in periods)’ = 6. Type: Number Length: 3 | AE5: Useful Life (in periods) The two fields ‘Useful Life (in years)’ and ‘Useful Life (in periods)’ are additive. For example, a useful life of 3.5 years would be maintained as ‘Useful Life (in years)’ = 3 and ‘Useful Life (in periods)’ = 6. Type: Number Length: 3 | AG5: Used life | AH5: Exp. usef. life in years at start of FY The portion of the useful life of the asset that has already expired. Type: Number Length: 3 | AI5: Exp. usef. life in perio. at start of FY The portion of the useful life of the asset that has already expired. Type: Number Length: 3 | AJ5: Asset Scrap Value You can specify an absolute amount here which cannot be depreciated in this depreciation area (memo value). If you specify a value here, then the cut-off value percentage determined on the basis of the cut-off value key in the depreciation key will not be taken into account. Even if no cut-off key is defined, depreciation will stop when this value is reached. Depending on how the cut-off value key is defined, this amount is either deducted from the depreciation base value before the start of depreciation, or depreciation is stopped as soon as this amount is reached. Type: Number Length: 23 Decimal: 2 | AK5: Scrap Value as Percentage of APC Type: Number Length: 14 Decimal: 11 | AL5: Cumulated Acquisition Value Please enter one row for each depreciation area. Type: Number Length: 23 Decimal: 2 | AN5: Accumulated Ordinary Depreciation Must be negative, e.g. -1267,00, in most of the business cases. Type: Number Length: 23 Decimal: 2 | AP5: Posted Ordinary Deprec. for the Year Depreciation values must be negative, e.g. -1234,56 and corrections of depreciation values positve, e.g. 1234,56. Type: Number Length: 23 Decimal: 2
A6: INO1 | B6: 1131400080 | E6: 0 | F6: 9001 | G6: Factory Building | H6: 9001000001 | I6: Buildings & Admin | J6: 1202010202 | L6: Factory Building-1 | O6: 1 | P6: EA | Q6: X | S6: 38078 | T6: 43191 | Y6: 2018 | Z6: 6450000 | AA6: 01 | AB6: ZSLM | AC6: 5840 | AD6: 16 | AE6: 0 | AG6: =_xlfn.CONCAT(AH6," years ",AI6," days") -> 6 years 277 days | AH6: 6 | AI6: 277 | AJ6: 0 | AK6: 0 | AL6: 6450000 | AM6: =ROUND(AL6,2) -> 6450000 | AN6: 2724683 | AO6: =ROUND(AN6,2)*-1 -> -2724683 | AP6: 199906.04 | AQ6: =ROUND(AP6,2)*-1 -> -199906.04
A7: INO1 | B7: 1131400212 | E7: 0 | F7: 9001 | G7: Factory Building | H7: 9001000001 | I7: Buildings & Admin | J7: 1202010202 | L7: Factory Building-2 | O7: 1 | P7: EA | Q7: X | S7: 39142 | T7: 43191 | Y7: 2018 | Z7: 5025000 | AA7: 01 | AB7: ZSLM | AC7: 6899 | AD7: 18 | AE7: 11 | AG7: =_xlfn.CONCAT(AH7," years ",AI7," days") -> 6 years 277 days | AH7: 6 | AI7: 277 | AJ7: 0 | AK7: 0 | AL7: 5025000 | AM7: =ROUND(AL7,2) -> 5025000 | AN7: 1796880 | AO7: =ROUND(AN7,2)*-1 -> -1796880 | AP7: 131834.31 | AQ7: =ROUND(AP7,2)*-1 -> -131834.31
A8: INO1 | B8: 1131400574 | E8: 0 | F8: 9001 | G8: Factory Building | H8: 9001000001 | I8: Buildings & Admin | J8: 1202010202 | L8: Factory Building-3 | O8: 1 | P8: EA | Q8: X | S8: 40574 | T8: 43191 | Y8: 2018 | Z8: 1400000 | AA8: 01 | AB8: ZSLM | AC8: 8322 | AD8: 22 | AE8: 10 | AG8: =_xlfn.CONCAT(AH8," years ",AI8," days") -> 6 years 277 days | AH8: 6 | AI8: 277 | AJ8: 0 | AK8: 0 | AL8: 1400000 | AM8: =ROUND(AL8,2) -> 1400000 | AN8: 415020 | AO8: =ROUND(AN8,2)*-1 -> -415020 | AP8: 30449.839 | AQ8: =ROUND(AP8,2)*-1 -> -30449.84
A9: INO1 | B9: 1131400670 | E9: 0 | F9: 9001 | G9: Factory Building | H9: 9001000001 | I9: Buildings & Admin | J9: 1202010202 | L9: Factory Building-4 | O9: 1 | P9: EA | Q9: X | S9: 40847 | T9: 43191 | Y9: 2018 | Z9: 2575000 | AA9: 01 | AB9: ZSLM | AC9: 8614 | AD9: 23 | AE9: 7 | AG9: =_xlfn.CONCAT(AH9," years ",AI9," days") -> 6 years 277 days | AH9: 6 | AI9: 277 | AJ9: 0 | AK9: 0 | AL9: 2575000 | AM9: =ROUND(AL9,2) -> 2575000 | AN9: 737465 | AO9: =ROUND(AN9,2)*-1 -> -737465 | AP9: 54106.86 | AQ9: =ROUND(AP9,2)*-1 -> -54106.86
A10: INO1 | B10: 1131400713 | E10: 0 | F10: 9001 | G10: Factory Building | H10: 9001000001 | I10: Buildings & Admin | J10: 1202010202 | L10: Factory Building-5 | O10: 1 | P10: EA | Q10: X | S10: 40999 | T10: 43191 | Y10: 2018 | Z10: 3250000 | AA10: 01 | AB10: ZSLM | AC10: 8760 | AD10: 24 | AE10: 0 | AG10: =_xlfn.CONCAT(AH10," years ",AI10," days") -> 6 years 277 days | AH10: 6 | AI10: 277 | AJ10: 0 | AK10: 0 | AL10: 3250000 | AM10: =ROUND(AL10,2) -> 3250000 | AN10: 915268 | AO10: =ROUND(AN10,2)*-1 -> -915268 | AP10: 67152.091 | AQ10: =ROUND(AP10,2)*-1 -> -67152.09
A11: INO1 | B11: 1131400975 | E11: 0 | F11: 9001 | G11: Factory Building | H11: 9001000001 | I11: Buildings & Admin | J11: 1202010202 | L11: Factory Building-6 | O11: 1 | P11: EA | Q11: X | S11: 41364 | T11: 43191 | Y11: 2018 | Z11: 16925000 | AA11: 01 | AB11: ZSLM | AC11: 9125 | AD11: 25 | AE11: 0 | AG11: =_xlfn.CONCAT(AH11," years ",AI11," days") -> 6 years 277 days | AH11: 6 | AI11: 277 | AJ11: 0 | AK11: 0 | AL11: 16925000 | AM11: =ROUND(AL11,2) -> 16925000 | AN11: 4575778 | AO11: =ROUND(AN11,2)*-1 -> -4575778 | AP11: 335717.89 | AQ11: =ROUND(AP11,2)*-1 -> -335717.89
A12: INO1 | B12: 1131401678 | E12: 0 | F12: 9001 | G12: Factory Building | H12: 9001000001 | I12: Buildings & Admin | J12: 1202010202 | L12: Toilet Line Orrisa Pan Fitting with Pipe Lin-7 | M12: e Complete | O12: 4 | P12: EA | Q12: X | S12: 42217 | T12: 43191 | Y12: 2018 | Z12: 55000 | AA12: 01 | AB12: ZSLM | AC12: 9965 | AD12: 27 | AE12: 4 | AG12: =_xlfn.CONCAT(AH12," years ",AI12," days") -> 6 years 277 days | AH12: 6 | AI12: 277 | AJ12: 0 | AK12: 0 | AL12: 55000 | AM12: =ROUND(AL12,2) -> 55000 | AN12: 13616 | AO12: =ROUND(AN12,2)*-1 -> -13616 | AP12: 999.15304 | AQ12: =ROUND(AP12,2)*-1 -> -999.15
A13: INO1 | B13: 1131100078 | E13: 0 | F13: 9001 | G13: Factory Building | H13: 9001000001 | I13: Buildings & Admin | J13: 1202010202 | L13: Factory Building-8 | O13: 1 | P13: EA | Q13: X | S13: 38078 | T13: 43191 | Y13: 2018 | Z13: 22975000 | AA13: 01 | AB13: ZSLM | AC13: 5840 | AD13: 16 | AE13: 0 | AG13: =_xlfn.CONCAT(AH13," years ",AI13," days") -> 6 years 277 days | AH13: 6 | AI13: 277 | AJ13: 0 | AK13: 0 | AL13: 22975000 | AM13: =ROUND(AL13,2) -> 22975000 | AN13: 9705364 | AO13: =ROUND(AN13,2)*-1 -> -9705364 | AP13: 712067.51 | AQ13: =ROUND(AP13,2)*-1 -> -712067.51
A14: INO1 | B14: 1131100083 | E14: 0 | F14: 9001 | G14: Factory Building | H14: 9001000001 | I14: Buildings & Admin | J14: 1202010202 | L14: Factory Building-9 | O14: 1 | P14: EA | Q14: X | S14: 38107 | T14: 43191 | Y14: 2018 | Z14: 130000 | AA14: 01 | AB14: ZSLM | AC14: 5877 | AD14: 16 | AE14: 1 | AG14: =_xlfn.CONCAT(AH14," years ",AI14," days") -> 6 years 277 days | AH14: 6 | AI14: 277 | AJ14: 0 | AK14: 0 | AL14: 130000 | AM14: =ROUND(AL14,2) -> 130000 | AN14: 54570 | AO14: =ROUND(AN14,2)*-1 -> -54570 | AP14: 4004.1024 | AQ14: =ROUND(AP14,2)*-1 -> -4004.1
A15: INO1 | B15: 1131100087 | E15: 0 | F15: 9001 | G15: Factory Building | H15: 9001000001 | I15: Buildings & Admin | J15: 1202010202 | L15: Factory Building-10 | O15: 1 | P15: EA | Q15: X | S15: 38138 | T15: 43191 | Y15: 2018 | Z15: 390000 | AA15: 01 | AB15: ZSLM | AC15: 5913 | AD15: 16 | AE15: 2 | AG15: =_xlfn.CONCAT(AH15," years ",AI15," days") -> 6 years 277 days | AH15: 6 | AI15: 277 | AJ15: 0 | AK15: 0 | AL15: 390000 | AM15: =ROUND(AL15,2) -> 390000 | AN15: 162714 | AO15: =ROUND(AN15,2)*-1 -> -162714 | AP15: 11938.461 | AQ15: =ROUND(AP15,2)*-1 -> -11938.46
A16: INO1 | B16: 1131100092 | E16: 0 | F16: 9001 | G16: Factory Building | H16: 9001000001 | I16: Buildings & Admin | J16: 1202010202 | L16: Factory Building-11 | O16: 1 | P16: EA | Q16: X | S16: 38168 | T16: 43191 | Y16: 2018 | Z16: 105000 | AA16: 01 | AB16: ZSLM | AC16: 5913 | AD16: 16 | AE16: 2 | AG16: =_xlfn.CONCAT(AH16," years ",AI16," days") -> 6 years 277 days | AH16: 6 | AI16: 277 | AJ16: 0 | AK16: 0 | AL16: 105000 | AM16: =ROUND(AL16,2) -> 105000 | AN16: 43808 | AO16: =ROUND(AN16,2)*-1 -> -43808 | AP16: 3213.8163 | AQ16: =ROUND(AP16,2)*-1 -> -3213.82
A17: INO1 | B17: 1131100094 | E17: 0 | F17: 9001 | G17: Factory Building | H17: 9001000001 | I17: Buildings & Admin | J17: 1202010202 | L17: Factory Building-12 | O17: 1 | P17: EA | Q17: X | S17: 38220 | T17: 43191 | Y17: 2018 | Z17: 530000 | AA17: 01 | AB17: ZSLM | AC17: 5986 | AD17: 16 | AE17: 5 | AG17: =_xlfn.CONCAT(AH17," years ",AI17," days") -> 6 years 277 days | AH17: 6 | AI17: 277 | AJ17: 0 | AK17: 0 | AL17: 530000 | AM17: =ROUND(AL17,2) -> 530000 | AN17: 218428 | AO17: =ROUND(AN17,2)*-1 -> -218428 | AP17: 16025.725 | AQ17: =ROUND(AP17,2)*-1 -> -16025.73
A18: INO1 | B18: 1131100100 | E18: 0 | F18: 9001 | G18: Factory Building | H18: 9001000001 | I18: Buildings & Admin | J18: 1202010202 | L18: Factory Building-13 | O18: 1 | P18: EA | Q18: X | S18: 38260 | T18: 43191 | Y18: 2018 | Z18: 520000 | AA18: 01 | AB18: ZSLM | AC18: 6023 | AD18: 16 | AE18: 6 | AG18: =_xlfn.CONCAT(AH18," years ",AI18," days") -> 6 years 277 days | AH18: 6 | AI18: 277 | AJ18: 0 | AK18: 0 | AL18: 520000 | AM18: =ROUND(AL18,2) -> 520000 | AN18: 212990 | AO18: =ROUND(AN18,2)*-1 -> -212990 | AP18: 15626.968 | AQ18: =ROUND(AP18,2)*-1 -> -15626.97
A19: INO1 | B19: 1131100110 | E19: 0 | F19: 9001 | G19: Factory Building | H19: 9001000001 | I19: Buildings & Admin | J19: 1202010202 | L19: Factory Building-14 | O19: 1 | P19: EA | Q19: X | S19: 38352 | T19: 43191 | Y19: 2018 | Z19: 160000 | AA19: 01 | AB19: ZSLM | AC19: 6096 | AD19: 16 | AE19: 9 | AG19: =_xlfn.CONCAT(AH19," years ",AI19," days") -> 6 years 277 days | AH19: 6 | AI19: 277 | AJ19: 0 | AK19: 0 | AL19: 160000 | AM19: =ROUND(AL19,2) -> 160000 | AN19: 64751 | AO19: =ROUND(AN19,2)*-1 -> -64751 | AP19: 4750.3123 | AQ19: =ROUND(AP19,2)*-1 -> -4750.31
A20: INO1 | B20: 1131100116 | E20: 0 | F20: 9001 | G20: Factory Building | H20: 9001000001 | I20: Buildings & Admin | J20: 1202010202 | L20: Factory Building-15 | O20: 1 | P20: EA | Q20: X | S20: 38383 | T20: 43191 | Y20: 2018 | Z20: 115000 | AA20: 01 | AB20: ZSLM | AC20: 6132 | AD20: 16 | AE20: 10 | AG20: =_xlfn.CONCAT(AH20," years ",AI20," days") -> 6 years 277 days | AH20: 6 | AI20: 277 | AJ20: 0 | AK20: 0 | AL20: 115000 | AM20: =ROUND(AL20,2) -> 115000 | AN20: 46266 | AO20: =ROUND(AN20,2)*-1 -> -46266 | AP20: 3394.7958 | AQ20: =ROUND(AP20,2)*-1 -> -3394.8
A21: INO1 | B21: 1131100119 | E21: 0 | F21: 9001 | G21: Factory Building | H21: 9001000001 | I21: Buildings & Admin | J21: 1202010202 | L21: Factory Building-16 | O21: 1 | P21: EA | Q21: X | S21: 38411 | T21: 43191 | Y21: 2018 | Z21: 630000 | AA21: 01 | AB21: ZSLM | AC21: 6169 | AD21: 16 | AE21: 11 | AG21: =_xlfn.CONCAT(AH21," years ",AI21," days") -> 6 years 277 days | AH21: 6 | AI21: 277 | AJ21: 0 | AK21: 0 | AL21: 630000 | AM21: =ROUND(AL21,2) -> 630000 | AN21: 251939 | AO21: =ROUND(AN21,2)*-1 -> -251939 | AP21: 18484.083 | AQ21: =ROUND(AP21,2)*-1 -> -18484.08
A22: INO1 | B22: 1131100122 | E22: 0 | F22: 9001 | G22: Factory Building | H22: 9001000001 | I22: Buildings & Admin | J22: 1202010202 | L22: Factory Building-17 | O22: 1 | P22: EA | Q22: X | S22: 38442 | T22: 43191 | Y22: 2018 | Z22: 540000 | AA22: 01 | AB22: ZSLM | AC22: 6205 | AD22: 17 | AE22: 0 | AG22: =_xlfn.CONCAT(AH22," years ",AI22," days") -> 6 years 277 days | AH22: 6 | AI22: 277 | AJ22: 0 | AK22: 0 | AL22: 540000 | AM22: =ROUND(AL22,2) -> 540000 | AN22: 214695 | AO22: =ROUND(AN22,2)*-1 -> -214695 | AP22: 15751.414 | AQ22: =ROUND(AP22,2)*-1 -> -15751.41
A23: INO1 | B23: 1131100400 | E23: 0 | F23: 9001 | G23: Factory Building | H23: 9001000001 | I23: Buildings & Admin | J23: 1202010202 | L23: Factory Building-18 | O23: 1 | P23: EA | Q23: X | S23: 40147 | T23: 43191 | Y23: 2018 | Z23: 2750000 | AA23: 01 | AB23: ZSLM | AC23: 7921 | AD23: 21 | AE23: 9 | AG23: =_xlfn.CONCAT(AH23," years ",AI23," days") -> 6 years 277 days | AH23: 6 | AI23: 277 | AJ23: 0 | AK23: 0 | AL23: 2750000 | AM23: =ROUND(AL23,2) -> 2750000 | AN23: 856489 | AO23: =ROUND(AN23,2)*-1 -> -856489 | AP23: 62839.368 | AQ23: =ROUND(AP23,2)*-1 -> -62839.37
A24: INO1 | B24: 1131100497 | E24: 0 | F24: 9001 | G24: Factory Building | H24: 9001000001 | I24: Buildings & Admin | J24: 1202010202 | L24: Factory Building-19 | O24: 1 | P24: EA | Q24: X | S24: 40446 | T24: 43191 | Y24: 2018 | Z24: 1875000 | AA24: 01 | AB24: ZSLM | AC24: 8213 | AD24: 22 | AE24: 6 | AG24: =_xlfn.CONCAT(AH24," years ",AI24," days") -> 6 years 277 days | AH24: 6 | AI24: 277 | AJ24: 0 | AK24: 0 | AL24: 1875000 | AM24: =ROUND(AL24,2) -> 1875000 | AN24: 563208 | AO24: =ROUND(AN24,2)*-1 -> -563208 | AP24: 41321.405 | AQ24: =ROUND(AP24,2)*-1 -> -41321.4
... A26: INO1 | B26: 1131101359 | E26: 0 | F26: 9001 | G26: Factory Building | H26: 9001000001 | I26: Buildings & Admin | J26: 1202010202 | L26: Factory Building-21 | O26: 1 | P26: EA | Q26: X | S26: 41716 | T26: 43191 | Y26: 2018 | Z26: 510000 | AA26: 01 | AB26: ZSLM | AC26: 9490 | AD26: 26 | AE26: 0 | AG26: =_xlfn.CONCAT(AH26," years ",AI26," days") -> 6 years 277 days | AH26: 6 | AI26: 277 | AJ26: 0 | AK26: 0 | AL26: 510000 | AM26: =ROUND(AL26,2) -> 510000 | AN26: 132579 | AO26: =ROUND(AN26,2)*-1 -> -132579 | AP26: 9726.5848 | AQ26: =ROUND(AP26,2)*-1 -> -9726.58
A27: INO1 | B27: 1131402939 | E27: 0 | F27: 9001 | G27: Factory Building | H27: 9001000002 | I27: Buildings & Admin | J27: 1202010202 | L27: BEING NON WALKABLE METAL CEILINGCAPITALISED -22 | M27: VIDE PURCHASE FROM ROYAL AIRCON BILL NO 286 DTD | O27: 1 | P27: EA | Q27: X | S27: 43577 | T27: 43577 | Y27: 2019 | Z27: 103395 | AA27: 01 | AB27: ZSLM | AC27: 10950 | AD27: 30 | AE27: 0 | AG27: =_xlfn.CONCAT(AH27," years ",AI27," days") -> 5 years 256 days | AH27: 5 | AI27: 256 | AJ27: 0 | AK27: 0 | AL27: 103395 | AM27: =ROUND(AL27,2) -> 103395 | AN27: 19650 | AO27: =ROUND(AN27,2)*-1 -> -19650 | AP27: 1708.8575 | AQ27: =ROUND(AP27,2)*-1 -> -1708.86
A28: INO1 | B28: 1131403183 | E28: 0 | F28: 9001 | G28: Factory Building | H28: 9001000002 | I28: Buildings & Admin | J28: 1202010202 | L28: Being Non Walkable Metal Ceiling fitting wor-23 | M28: k done | O28: 1 | P28: EA | Q28: X | S28: 43817 | T28: 43817 | Y28: 2019 | Z28: 576753 | AA28: 01 | AB28: ZSLM | AC28: 10950 | AD28: 30 | AE28: 0 | AG28: =_xlfn.CONCAT(AH28," years ",AI28," days") -> 5 years 16 days | AH28: 5 | AI28: 16 | AJ28: 0 | AK28: 0 | AL28: 576753 | AM28: =ROUND(AL28,2) -> 576753 | AN28: 96968 | AO28: =ROUND(AN28,2)*-1 -> -96968 | AP28: 9533.7868 | AQ28: =ROUND(AP28,2)*-1 -> -9533.79
A29: INO1 | B29: 1131403175 | E29: 0 | F29: 9001 | G29: Factory Building | H29: 9001000002 | I29: Buildings & Admin | J29: 1202010202 | L29: Being HR Sheets & HR Plates pur from Gayatri-24 | M29: Steel & Pipes vide inv no 0969 dt 27.11.19 ag P | O29: 1 | P29: EA | Q29: X | S29: 43801 | T29: 43801 | Y29: 2019 | Z29: 200669 | AA29: 01 | AB29: ZSLM | AC29: 10950 | AD29: 30 | AE29: 0 | AG29: =_xlfn.CONCAT(AH29," years ",AI29," days") -> 5 years 32 days | AH29: 5 | AI29: 32 | AJ29: 0 | AK29: 0 | AL29: 200669 | AM29: =ROUND(AL29,2) -> 200669 | AN29: 33143 | AO29: =ROUND(AN29,2)*-1 -> -33143 | AP29: 3317.2282 | AQ29: =ROUND(AP29,2)*-1 -> -3317.23
A30: INO1 | B30: 1131403093 | E30: 0 | F30: 9001 | G30: Factory Building | H30: 9001000003 | I30: Buildings & Admin | J30: 1202010202 | L30: Being Construction work done by Jai Mata Con-25 | M30: struction vide inv no 09 dt 05.11.19 ag PO# SMPO | O30: 1 | P30: EA | Q30: X | S30: 43781 | T30: 43781 | Y30: 2019 | Z30: 733982 | AA30: 01 | AB30: ZSLM | AC30: 10950 | AD30: 30 | AE30: 0 | AG30: =_xlfn.CONCAT(AH30," years ",AI30," days") -> 5 years 52 days | AH30: 5 | AI30: 52 | AJ30: 0 | AK30: 0 | AL30: 733982 | AM30: =ROUND(AL30,2) -> 733982 | AN30: 125816 | AO30: =ROUND(AN30,2)*-1 -> -125816 | AP30: 12132.398 | AQ30: =ROUND(AP30,2)*-1 -> -12132.4
A31: INO1 | B31: 1131403088 | E31: 0 | F31: 9001 | G31: Factory Building | H31: 9001000004 | I31: Buildings & Admin | J31: 1202010202 | L31: Being 3mm Epoxy Flooring work done by H A M -26 | M31: Corporation vide inv no 47 dt 09.11.19 ag PO# SM | O31: 1 | P31: EA | Q31: X | S31: 43771 | T31: 43771 | Y31: 2019 | Z31: 457331 | AA31: 01 | AB31: ZSLM | AC31: 10950 | AD31: 30 | AE31: 0 | AG31: =_xlfn.CONCAT(AH31," years ",AI31," days") -> 5 years 62 days | AH31: 5 | AI31: 62 | AJ31: 0 | AK31: 0 | AL31: 457331 | AM31: =ROUND(AL31,2) -> 457331 | AN31: 78811 | AO31: =ROUND(AN31,2)*-1 -> -78811 | AP31: 7559.8226 | AQ31: =ROUND(AP31,2)*-1 -> -7559.82
A32: INO1 | B32: 1131403188 | E32: 0 | F32: 9001 | G32: Factory Building | H32: 9001000004 | I32: Buildings & Admin | J32: 1202010202 | L32: Being 3mm Epoxy Flooring work done by HAM Co-27 | M32: rporation vide inv no 57 dt 16.12.19 ag PO# SMPO | O32: 1 | P32: EA | Q32: X | S32: 43821 | T32: 43821 | Y32: 2019 | Z32: 111953 | AA32: 01 | AB32: ZSLM | AC32: 10950 | AD32: 30 | AE32: 0 | AG32: =_xlfn.CONCAT(AH32," years ",AI32," days") -> 5 years 12 days | AH32: 5 | AI32: 12 | AJ32: 0 | AK32: 0 | AL32: 111953 | AM32: =ROUND(AL32,2) -> 111953 | AN32: 18782 | AO32: =ROUND(AN32,2)*-1 -> -18782 | AP32: 1850.0689 | AQ32: =ROUND(AP32,2)*-1 -> -1850.07
A33: INO1 | B33: 1131403286 | E33: 0 | F33: 9001 | G33: Factory Building | H33: 9001000005 | I33: Buildings & Admin | J33: 1202010202 | L33: Being New Compound wall work done by Pyramid-28 | M33: Construction vide inv no 3 dt 04.02.20 ag PO# S | O33: 1 | P33: EA | Q33: X | S33: 43931 | T33: 43931 | Y33: 2020 | Z33: 790821 | AA33: 01 | AB33: ZSLM | AC33: 10950 | AD33: 30 | AE33: 0 | AG33: =_xlfn.CONCAT(AH33," years ",AI33," days") -> 4 years 267 days | AH33: 4 | AI33: 267 | AJ33: 0 | AK33: 0 | AL33: 790821 | AM33: =ROUND(AL33,2) -> 790821 | AN33: 124726 | AO33: =ROUND(AN33,2)*-1 -> -124726 | AP33: 13071.851 | AQ33: =ROUND(AP33,2)*-1 -> -13071.85
A34: INO1 | B34: 1131403288 | E34: 0 | F34: 9001 | G34: Factory Building | H34: 9001000006 | I34: Buildings & Admin | J34: 1202010202 | L34: Being MS Round & Square Bar pur from Sainath-29 | M34: Structures Pvt Ltd vide inv no GST3983 dt 08.01 | O34: 1 | P34: EA | Q34: X | S34: 43931 | T34: 43931 | Y34: 2020 | Z34: 32667 | AA34: 01 | AB34: ZSLM | AC34: 10950 | AD34: 30 | AE34: 0 | AG34: =_xlfn.CONCAT(AH34," years ",AI34," days") -> 4 years 267 days | AH34: 4 | AI34: 267 | AJ34: 0 | AK34: 0 | AL34: 32667 | AM34: =ROUND(AL34,2) -> 32667 | AN34: 5152 | AO34: =ROUND(AN34,2)*-1 -> -5152 | AP34: 540.11288 | AQ34: =ROUND(AP34,2)*-1 -> -540.11
A35: INO1 | B35: 1131403289 | E35: 0 | F35: 9001 | G35: Factory Building | H35: 9001000006 | I35: Buildings & Admin | J35: 1202010202 | L35: Being Main Gate Office Side Old Road RCC Ruf-30 | M35: f work done by Jai Mata Construction vide inv no | O35: 1 | P35: EA | Q35: X | S35: 43931 | T35: 43931 | Y35: 2020 | Z35: 216737 | AA35: 01 | AB35: ZSLM | AC35: 10950 | AD35: 30 | AE35: 0 | AG35: =_xlfn.CONCAT(AH35," years ",AI35," days") -> 4 years 267 days | AH35: 4 | AI35: 267 | AJ35: 0 | AK35: 0 | AL35: 216737 | AM35: =ROUND(AL35,2) -> 216737 | AN35: 34183 | AO35: =ROUND(AN35,2)*-1 -> -34183 | AP35: 3582.68 | AQ35: =ROUND(AP35,2)*-1 -> -3582.68
A36: INO1 | B36: 1131403491 | E36: 0 | F36: 9001 | G36: Factory Building | H36: 9001000007 | I36: Buildings & Admin | J36: 1202010202 | L36: Being MS Chanel, Chakar Plate, MS angle, MS -31 | M36: Pipes pur from Sainath Structures Pvt Ltd vide i | O36: 1 | P36: EA | Q36: X | S36: 44183 | T36: 44183 | Y36: 2020 | Z36: 67468 | AA36: 01 | AB36: ZSLM | AC36: 10950 | AD36: 30 | AE36: 0 | AG36: =_xlfn.CONCAT(AH36," years ",AI36," days") -> 4 years 15 days | AH36: 4 | AI36: 15 | AJ36: 0 | AK36: 0 | AL36: 67468 | AM36: =ROUND(AL36,2) -> 67468 | AN36: 9088 | AO36: =ROUND(AN36,2)*-1 -> -9088 | AP36: 1115.3797 | AQ36: =ROUND(AP36,2)*-1 -> -1115.38
A37: INO1 | B37: 1131403492 | E37: 0 | F37: 9001 | G37: Factory Building | H37: 9001000007 | I37: Buildings & Admin | J37: 1202010202 | L37: Being Fabrication Work for Extra Receiver In-32 | M37: stallation for Header Connecting With Support Wo | O37: 1 | P37: EA | Q37: X | S37: 44185 | T37: 44185 | Y37: 2020 | Z37: 19636 | AA37: 01 | AB37: ZSLM | AC37: 10950 | AD37: 30 | AE37: 0 | AG37: =_xlfn.CONCAT(AH37," years ",AI37," days") -> 4 years 13 days | AH37: 4 | AI37: 13 | AJ37: 0 | AK37: 0 | AL37: 19636 | AM37: =ROUND(AL37,2) -> 19636 | AN37: 2641 | AO37: =ROUND(AN37,2)*-1 -> -2641 | AP37: 325.02228 | AQ37: =ROUND(AP37,2)*-1 -> -325.02
A38: INO1 | B38: 1131403486 | E38: 0 | F38: 9001 | G38: Factory Building | H38: 9001000007 | I38: Buildings & Admin | J38: 1202010202 | L38: Being PARKING SHADE FABRICATION WORK DONE FO-33 | M38: R NEW PLANT pur from Grace Engineering Works vid | O38: 1 | P38: EA | Q38: X | S38: 44177 | T38: 44177 | Y38: 2020 | Z38: 31242 | AA38: 01 | AB38: ZSLM | AC38: 10950 | AD38: 30 | AE38: 0 | AG38: =_xlfn.CONCAT(AH38," years ",AI38," days") -> 4 years 21 days | AH38: 4 | AI38: 21 | AJ38: 0 | AK38: 0 | AL38: 31242 | AM38: =ROUND(AL38,2) -> 31242 | AN38: 4226 | AO38: =ROUND(AN38,2)*-1 -> -4226 | AP38: 515.93644 | AQ38: =ROUND(AP38,2)*-1 -> -515.94
... A53: INO1 | B53: 1131404646 | E53: 0 | F53: 9001 | G53: Factory Building | H53: 9001000016 | I53: Buildings & Admin | J53: 1202010202 | L53: Addition to New Building (Addition to New Pl-48 | M53: ant) | O53: 1 | P53: EA | Q53: X | S53: 44986 | T53: 44986 | Y53: 2023 | Z53: 1.5146637e+08 | AA53: 01 | AB53: ZSLM | AC53: 10950 | AD53: 30 | AE53: 0 | AG53: =_xlfn.CONCAT(AH53," years ",AI53," days") -> 1 years 307 days | AH53: 1 | AI53: 307 | AJ53: 0 | AK53: 0 | AL53: 1.5146637e+08 | AM53: =ROUND(AL53,2) -> 1.5146637e+08 | AN53: 9295470 | AO53: =ROUND(AN53,2)*-1 -> -9295470 | AP53: 2503690.7 | AQ53: =ROUND(AP53,2)*-1 -> -2503690.7
A54: INO1 | B54: 1131404732 | E54: 0 | F54: 9001 | G54: Factory Building | H54: 9001000017 | I54: Buildings & Admin | J54: 1202010202 | L54: Improvement In Factory Building-49 | O54: 1 | P54: EA | Q54: X | S54: 45047 | T54: 45047 | Y54: 2023 | Z54: 3552291.3 | AA54: 01 | AB54: ZSLM | AC54: 10950 | AD54: 30 | AE54: 0 | AG54: =_xlfn.CONCAT(AH54," years ",AI54," days") -> 1 years 246 days | AH54: 1 | AI54: 246 | AJ54: 0 | AK54: 0 | AL54: 3552291.3 | AM54: =ROUND(AL54,2) -> 3552291.3 | AN54: 198215 | AO54: =ROUND(AN54,2)*-1 -> -198215 | AP54: 58717.85 | AQ54: =ROUND(AP54,2)*-1 -> -58717.85
A55: INO1 | B55: 1131404801 | E55: 0 | F55: 9001 | G55: Factory Building | H55: 9001000017 | I55: Buildings & Admin | J55: 1202010202 | L55: B/NO. 033 DT: 15.06.23 OF GRACE ENGINEERING -50 | M55: WORKS BOOKED FOR STP PLANT ROOF MAKING , JALLY | O55: 1 | P55: EA | Q55: X | S55: 45108 | T55: 45108 | Y55: 2023 | Z55: 47780 | AA55: 01 | AB55: ZSLM | AC55: 10950 | AD55: 30 | AE55: 0 | AG55: =_xlfn.CONCAT(AH55," years ",AI55," days") -> 1 years 185 days | AH55: 1 | AI55: 185 | AJ55: 0 | AK55: 0 | AL55: 47780 | AM55: =ROUND(AL55,2) -> 47780 | AN55: 2400 | AO55: =ROUND(AN55,2)*-1 -> -2400 | AP55: 789.6968 | AQ55: =ROUND(AP55,2)*-1 -> -789.7
A56: INO1 | B56: 1131404809 | E56: 0 | F56: 9001 | G56: Factory Building | H56: 9001000017 | I56: Buildings & Admin | J56: 1202010202 | L56: B/NO. 43 DT: 03.07.23 OF PRAFULLA SHEET BOOK-51 | M56: ED FOR PVC PIPE RAIN WATER LINE FITTING , ELBOW | O56: 1 | P56: EA | Q56: X | S56: 45111 | T56: 45111 | Y56: 2023 | Z56: 34522 | AA56: 01 | AB56: ZSLM | AC56: 10950 | AD56: 30 | AE56: 0 | AG56: =_xlfn.CONCAT(AH56," years ",AI56," days") -> 1 years 182 days | AH56: 1 | AI56: 182 | AJ56: 0 | AK56: 0 | AL56: 34522 | AM56: =ROUND(AL56,2) -> 34522 | AN56: 1725 | AO56: =ROUND(AN56,2)*-1 -> -1725 | AP56: 570.16128 | AQ56: =ROUND(AP56,2)*-1 -> -570.16
A57: INO1 | B57: 1131404920 | E57: 0 | F57: 9001 | G57: Factory Building | H57: 9001000018 | I57: Buildings & Admin | J57: 1202010202 | L57: Being Factory Building work Capitalised-52 | O57: 1 | P57: EA | Q57: X | S57: 45199 | T57: 45199 | Y57: 2023 | Z57: 9299379.8 | AA57: 01 | AB57: ZSLM | AC57: 10950 | AD57: 30 | AE57: 0 | AG57: =_xlfn.CONCAT(AH57," years ",AI57," days") -> 1 years 94 days | AH57: 1 | AI57: 94 | AJ57: 0 | AK57: 0 | AL57: 9299379.8 | AM57: =ROUND(AL57,2) -> 9299379.8 | AN57: 389810 | AO57: =ROUND(AN57,2)*-1 -> -389810 | AP57: 153715.39 | AQ57: =ROUND(AP57,2)*-1 -> -153715.39
A58: INO1 | B58: 1131404966 | E58: 0 | F58: 9001 | G58: Factory Building | H58: 9001000019 | I58: Buildings & Admin | J58: 1202010202 | L58: B/NO. 27 DT: 23.05.23 OF PANCHAL INDUSTRIES -53 | M58: BOOKED FOR PUR ROLLING SHUTTER VIDE TSGO/23-24/ | O58: 10 | P58: EA | Q58: X | S58: 45231 | T58: 45231 | Y58: 2023 | Z58: 474388 | AA58: 01 | AB58: ZSLM | AC58: 10950 | AD58: 30 | AE58: 0 | AG58: =_xlfn.CONCAT(AH58," years ",AI58," days") -> 1 years 62 days | AH58: 1 | AI58: 62 | AJ58: 0 | AK58: 0 | AL58: 474388 | AM58: =ROUND(AL58,2) -> 474388 | AN58: 18499 | AO58: =ROUND(AN58,2)*-1 -> -18499 | AP58: 7841.4479 | AQ58: =ROUND(AP58,2)*-1 -> -7841.45
A59: INO1 | B59: 1131404967 | E59: 0 | F59: 9001 | G59: Factory Building | H59: 9001000019 | I59: Buildings & Admin | J59: 1202010202 | L59: B/NO. 88 DT: 04.08.23 OF PANCHAL INDUSTRIES -54 | M59: BOOKED FOR PUR GLASS DOOR , RADAR & DIGITAL LOC | O59: 47 | P59: EA | Q59: X | S59: 45231 | T59: 45231 | Y59: 2023 | Z59: 153400 | AA59: 01 | AB59: ZSLM | AC59: 10950 | AD59: 30 | AE59: 0 | AG59: =_xlfn.CONCAT(AH59," years ",AI59," days") -> 1 years 62 days | AH59: 1 | AI59: 62 | AJ59: 0 | AK59: 0 | AL59: 153400 | AM59: =ROUND(AL59,2) -> 153400 | AN59: 5982 | AO59: =ROUND(AN59,2)*-1 -> -5982 | AP59: 2535.5525 | AQ59: =ROUND(AP59,2)*-1 -> -2535.55
A60: INO1 | B60: 1131404968 | E60: 0 | F60: 9001 | G60: Factory Building | H60: 9001000019 | I60: Buildings & Admin | J60: 1202010202 | L60: B/NO. 04 DT: 09.09.23 OF JAI MATA CONSTRUCTI-55 | M60: ON BOOKED FOR HT YARD 2500 KVA AREA WALL BREAKIN | O60: 1 | P60: EA | Q60: X | S60: 45231 | T60: 45231 | Y60: 2023 | Z60: 54042 | AA60: 01 | AB60: ZSLM | AC60: 10950 | AD60: 30 | AE60: 0 | AG60: =_xlfn.CONCAT(AH60," years ",AI60," days") -> 1 years 62 days | AH60: 1 | AI60: 62 | AJ60: 0 | AK60: 0 | AL60: 54042 | AM60: =ROUND(AL60,2) -> 54042 | AN60: 2107 | AO60: =ROUND(AN60,2)*-1 -> -2107 | AP60: 893.68822 | AQ60: =ROUND(AP60,2)*-1 -> -893.69
A61: INO1 | B61: 1131404969 | E61: 0 | F61: 9001 | G61: Factory Building | H61: 9001000019 | I61: Buildings & Admin | J61: 1202010202 | L61: B/NO. 05 DT: 11.09.23 OF JAI MATA CONSTRUCTI-56 | M61: ON BOOKED FOR ROAD EXCAVATION , RCC 200 MM THIK | O61: 1 | P61: EA | Q61: X | S61: 45231 | T61: 45231 | Y61: 2023 | Z61: 3211253 | AA61: 01 | AB61: ZSLM | AC61: 10950 | AD61: 30 | AE61: 0 | AG61: =_xlfn.CONCAT(AH61," years ",AI61," days") -> 1 years 62 days | AH61: 1 | AI61: 62 | AJ61: 0 | AK61: 0 | AL61: 3211253 | AM61: =ROUND(AL61,2) -> 3211253 | AN61: 125224 | AO61: =ROUND(AN61,2)*-1 -> -125224 | AP61: 53081.189 | AQ61: =ROUND(AP61,2)*-1 -> -53081.19
A62: INO1 | B62: 1131404970 | E62: 0 | F62: 9001 | G62: Factory Building | H62: 9001000019 | I62: Buildings & Admin | J62: 1202010202 | L62: B/NO. BILL/23-24/19 DT: 01.10.23 OF PK ENTER-57 | M62: PRISES BOOEKD FOR CIVIL WORK AGST PO SMPOCG/23-2 | O62: 1 | P62: EA | Q62: X | S62: 45231 | T62: 45231 | Y62: 2023 | Z62: 111523 | AA62: 01 | AB62: ZSLM | AC62: 10950 | AD62: 30 | AE62: 0 | AG62: =_xlfn.CONCAT(AH62," years ",AI62," days") -> 1 years 62 days | AH62: 1 | AI62: 62 | AJ62: 0 | AK62: 0 | AL62: 111523 | AM62: =ROUND(AL62,2) -> 111523 | AN62: 4349 | AO62: =ROUND(AN62,2)*-1 -> -4349 | AP62: 1843.3273 | AQ62: =ROUND(AP62,2)*-1 -> -1843.33
A63: INO1 | B63: 1131404971 | E63: 0 | F63: 9001 | G63: Factory Building | H63: 9001000019 | I63: Buildings & Admin | J63: 1202010202 | L63: B/NO. 08 DT: 05.10.23 OF JAI MATA CONSTRUCTI-58 | M63: ON BOOKED FOR ROAD EXCAVATION , GSB FILLING , ST | O63: 1 | P63: EA | Q63: X | S63: 45231 | T63: 45231 | Y63: 2023 | Z63: 625968 | AA63: 01 | AB63: ZSLM | AC63: 10950 | AD63: 30 | AE63: 0 | AG63: =_xlfn.CONCAT(AH63," years ",AI63," days") -> 1 years 62 days | AH63: 1 | AI63: 62 | AJ63: 0 | AK63: 0 | AL63: 625968 | AM63: =ROUND(AL63,2) -> 625968 | AN63: 24410 | AO63: =ROUND(AN63,2)*-1 -> -24410 | AP63: 10346.945 | AQ63: =ROUND(AP63,2)*-1 -> -10346.94
A64: INO1 | B64: 1131404972 | E64: 0 | F64: 9001 | G64: Factory Building | H64: 9001000019 | I64: Buildings & Admin | J64: 1202010202 | L64: B/NO. 354/23-24 DT: 06.10.23 OF LAXMI ELE BO-59 | M64: OKED FOR PU FLOORING AGST PO SMPOCG/23-24/202 DT | O64: 46 | P64: EA | Q64: X | S64: 45231 | T64: 45231 | Y64: 2023 | Z64: 80334 | AA64: 01 | AB64: ZSLM | AC64: 10950 | AD64: 30 | AE64: 0 | AG64: =_xlfn.CONCAT(AH64," years ",AI64," days") -> 1 years 62 days | AH64: 1 | AI64: 62 | AJ64: 0 | AK64: 0 | AL64: 80334 | AM64: =ROUND(AL64,2) -> 80334 | AN64: 3133 | AO64: =ROUND(AN64,2)*-1 -> -3133 | AP64: 1327.5545 | AQ64: =ROUND(AP64,2)*-1 -> -1327.55
A65: INO1 | B65: 1131404973 | E65: 0 | F65: 9001 | G65: Factory Building | H65: 9001000019 | I65: Buildings & Admin | J65: 1202010202 | L65: B/NO. 053 DT: 16.10.23 OF GRACE ENGINEERING-60 | M65: BOOKED FOR HAND RAILING MAKING OF UTILITY AGTS | O65: 1 | P65: EA | Q65: X | S65: 45231 | T65: 45231 | Y65: 2023 | Z65: 99120 | AA65: 01 | AB65: ZSLM | AC65: 10950 | AD65: 30 | AE65: 0 | AG65: =_xlfn.CONCAT(AH65," years ",AI65," days") -> 1 years 62 days | AH65: 1 | AI65: 62 | AJ65: 0 | AK65: 0 | AL65: 99120 | AM65: =ROUND(AL65,2) -> 99120 | AN65: 3865 | AO65: =ROUND(AN65,2)*-1 -> -3865 | AP65: 1638.6493 | AQ65: =ROUND(AP65,2)*-1 -> -1638.65
A66: INO1 | B66: 1131405014 | E66: 0 | F66: 9001 | G66: Factory Building | H66: 9001000020 | I66: Buildings & Admin | J66: 1202010202 | L66: BEING T/F THROUGH J/V AGST B/NO. S-123/2023--61 | M66: 24 DT: 10.10.23 OF PRAGMATIC HVAC BOOKED FOR PUR | O66: 67 | P66: EA | Q66: X | S66: 45261 | T66: 45261 | Y66: 2023 | Z66: 100327 | AA66: 01 | AB66: ZSLM | AC66: 10950 | AD66: 30 | AE66: 0 | AG66: =_xlfn.CONCAT(AH66," years ",AI66," days") -> 1 years 32 days | AH66: 1 | AI66: 32 | AJ66: 0 | AK66: 0 | AL66: 100327 | AM66: =ROUND(AL66,2) -> 100327 | AN66: 3637 | AO66: =ROUND(AN66,2)*-1 -> -3637 | AP66: 1658.7996 | AQ66: =ROUND(AP66,2)*-1 -> -1658.8
A67: INO1 | B67: 1131405015 | E67: 0 | F67: 9001 | G67: Factory Building | H67: 9001000020 | I67: Buildings & Admin | J67: 1202010202 | L67: BEING AMT T/F THROUGH J/V AGST B/NO. 1099 DT-62 | M67: : 06.11.23 OF SOLANKI ENTERPRISES BOOKED FOR PUR | O67: 2 | P67: EA | Q67: X | S67: 45261 | T67: 45261 | Y67: 2023 | Z67: 14160 | AA67: 01 | AB67: ZSLM | AC67: 10950 | AD67: 30 | AE67: 0 | AG67: =_xlfn.CONCAT(AH67," years ",AI67," days") -> 1 years 32 days | AH67: 1 | AI67: 32 | AJ67: 0 | AK67: 0 | AL67: 14160 | AM67: =ROUND(AL67,2) -> 14160 | AN67: 513 | AO67: =ROUND(AN67,2)*-1 -> -513 | AP67: 234.4411 | AQ67: =ROUND(AP67,2)*-1 -> -234.44
A68: INO1 | B68: 1131405075 | E68: 0 | F68: 9001 | G68: Factory Building | H68: 9001000021 | I68: Buildings & Admin | J68: 1202010202 | L68: BEING T/F THROUGH J/V AGTS B/NO. 075 DT: 22.-63 | M68: 01.24 OF GRACE ENGINEERING WORKS BOOKED FOR RAMP | O68: 1 | P68: EA | Q68: X | S68: 45314 | T68: 45314 | Y68: 2024 | Z68: 30007 | AA68: 01 | AB68: ZSLM | AC68: 10950 | AD68: 30 | AE68: 0 | AG68: =_xlfn.CONCAT(AH68," years ",AI68," days") -> 0 years 344 days | AH68: 0 | AI68: 344 | AJ68: 0 | AK68: 0 | AL68: 30007 | AM68: =ROUND(AL68,2) -> 30007 | AN68: 943 | AO68: =ROUND(AN68,2)*-1 -> -943 | AP68: 495.69178 | AQ68: =ROUND(AP68,2)*-1 -> -495.69
A69: INO1 | B69: 1131405107 | E69: 0 | F69: 9001 | G69: Factory Building | H69: 9001000022 | I69: Buildings & Admin | J69: 1202010202 | L69: BEING T/F THROUGH J/V AGST B/NO. BILL/23-24/-64 | M69: 30 DTD: 02.02.24 OF PK ENTERPRISES BOOKED FOR RC | O69: 1 | P69: EA | Q69: X | S69: 45345 | T69: 45345 | Y69: 2024 | Z69: 316483 | AA69: 01 | AB69: ZSLM | AC69: 10950 | AD69: 30 | AE69: 0 | AG69: =_xlfn.CONCAT(AH69," years ",AI69," days") -> 0 years 313 days | AH69: 0 | AI69: 313 | AJ69: 0 | AK69: 0 | AL69: 316483 | AM69: =ROUND(AL69,2) -> 316483 | AN69: 9047 | AO69: =ROUND(AN69,2)*-1 -> -9047 | AP69: 5230.8632 | AQ69: =ROUND(AP69,2)*-1 -> -5230.86
... A71: INO1 | B71: 1131405109 | E71: 0 | F71: 9001 | G71: Factory Building | H71: 9001000022 | I71: Buildings & Admin | J71: 1202010202 | L71: BEING T/F THROUGH J/V AGST B/NO. BILL/23-24/-66 | M71: 31 DTD: 02.02.24 OF P K ENTERPRISES BOOEKD FOR C | O71: 1 | P71: EA | Q71: X | S71: 45346 | T71: 45346 | Y71: 2024 | Z71: 1245065 | AA71: 01 | AB71: ZSLM | AC71: 10950 | AD71: 30 | AE71: 0 | AG71: =_xlfn.CONCAT(AH71," years ",AI71," days") -> 0 years 312 days | AH71: 0 | AI71: 312 | AJ71: 0 | AK71: 0 | AL71: 1245065 | AM71: =ROUND(AL71,2) -> 1245065 | AN71: 35476 | AO71: =ROUND(AN71,2)*-1 -> -35476 | AP71: 20580.351 | AQ71: =ROUND(AP71,2)*-1 -> -20580.35
A72: INO1 | B72: 1131405213 | E72: 0 | F72: 9001 | G72: Factory Building | H72: 9001000023 | I72: Buildings & Admin | J72: 1202010202 | L72: Fire hydrant Foam Monitor-67 | O72: 1 | P72: EA | Q72: X | S72: 45444 | T72: 45444 | Y72: 2024 | Z72: 102042 | AA72: 01 | AB72: ZSLM | AC72: 10950 | AD72: 30 | AE72: 0 | AG72: =_xlfn.CONCAT(AH72," years ",AI72," days") -> 0 years 214 days | AH72: 0 | AI72: 214 | AJ72: 0 | AK72: 0 | AL72: 102042 | AM72: =ROUND(AL72,2) -> 102042 | AN72: 1994 | AO72: =ROUND(AN72,2)*-1 -> -1994 | AP72: 1686.9671 | AQ72: =ROUND(AP72,2)*-1 -> -1686.97
A73: INO1 | B73: 1131405214 | E73: 0 | F73: 9001 | G73: Factory Building | H73: 9001000023 | I73: Buildings & Admin | J73: 1202010202 | L73: Being installation in new Security cabin & E-68 | M73: mergency control for Fire safety | O73: 1 | P73: EA | Q73: X | S73: 45453 | T73: 45453 | Y73: 2024 | Z73: 51201 | AA73: 01 | AB73: ZSLM | AC73: 10950 | AD73: 30 | AE73: 0 | AG73: =_xlfn.CONCAT(AH73," years ",AI73," days") -> 0 years 205 days | AH73: 0 | AI73: 205 | AJ73: 0 | AK73: 0 | AL73: 51201 | AM73: =ROUND(AL73,2) -> 51201 | AN73: 959 | AO73: =ROUND(AN73,2)*-1 -> -959 | AP73: 845.8937 | AQ73: =ROUND(AP73,2)*-1 -> -845.89
A74: INO1 | B74: 1131405260 | E74: 0 | F74: 9001 | G74: Factory Building | H74: 9001000024 | I74: Buildings & Admin | J74: 1202010202 | L74: Being Workers canteen ( New) Capitalised-69 | O74: 1 | P74: EA | Q74: X | S74: 45530 | T74: 45530 | Y74: 2024 | Z74: 838800 | AA74: 01 | AB74: ZSLM | AC74: 10950 | AD74: 30 | AE74: 0 | AG74: =_xlfn.CONCAT(AH74," years ",AI74," days") -> 0 years 128 days | AH74: 0 | AI74: 128 | AJ74: 0 | AK74: 0 | AL74: 838800 | AM74: =ROUND(AL74,2) -> 838800 | AN74: 9805 | AO74: =ROUND(AN74,2)*-1 -> -9805 | AP74: 13865.247 | AQ74: =ROUND(AP74,2)*-1 -> -13865.25
A75: INO1 | B75: 1131405261 | E75: 0 | F75: 9001 | G75: Factory Building | H75: 9001000025 | I75: Buildings & Admin | J75: 1202010202 | L75: BEING T/F THROUGH J/V AGST B/NO. BILL/25-26/-70 | M75: 05 DTD: 01.06.25 OF P K ENTERPRISES BOOEKD FOR | O75: 1 | P75: EA | Q75: X | S75: 45812 | T75: 45812 | Y75: 2025 | Z75: 0 | AA75: 01 | AB75: ZSLM | AC75: 10950 | AD75: 30 | AE75: 0 | AG75: =_xlfn.CONCAT(AH75," years ",AI75," days") -> 0 years 0 days | AH75: 0 | AI75: 0 | AJ75: 0 | AK75: 0 | AL75: 222190 | AM75: =ROUND(AL75,2) -> 222190 | AN75: 0 | AO75: =ROUND(AN75,2)*-1 -> 0 | AP75: 547.86575 | AQ75: =ROUND(AP75,2)*-1 -> -547.87
A76: INO1 | B76: 1131105131 | E76: 0 | F76: 9001 | G76: Factory Building | H76: 9001000026 | I76: Buildings & Admin | J76: 1202010202 | L76: Factory Building work Capitalised-71 | O76: 1 | P76: EA | Q76: X | S76: 45382 | T76: 45382 | Y76: 2024 | Z76: 5399840.7 | AA76: 01 | AB76: ZSLM | AC76: 10950 | AD76: 30 | AE76: 0 | AG76: =_xlfn.CONCAT(AH76," years ",AI76," days") -> 0 years 276 days | AH76: 0 | AI76: 276 | AJ76: 0 | AK76: 0 | AL76: 5399840.7 | AM76: =ROUND(AL76,2) -> 5399840.7 | AN76: 136599 | AO76: =ROUND(AN76,2)*-1 -> -136599 | AP76: 89257.35 | AQ76: =ROUND(AP76,2)*-1 -> -89257.35
A77: INO1 | B77: 1131400003 | E77: 0 | F77: 9002 | G77: Flat | H77: 9002000001 | I77: Buildings & Admin | J77: 1202010202 | L77: Flat (A-306 - Horizon)-72 | O77: 1 | P77: EA | Q77: X | S77: 36445 | T77: 43191 | Y77: 2018 | Z77: 1400000 | AA77: 01 | AB77: ZSLM | AC77: 11498 | AD77: 31 | AE77: 6 | AG77: =_xlfn.CONCAT(AH77," years ",AI77," days") -> 6 years 277 days | AH77: 6 | AI77: 277 | AJ77: 0 | AK77: 0 | AL77: 1400000 | AM77: =ROUND(AL77,2) -> 1400000 | AN77: 300383 | AO77: =ROUND(AN77,2)*-1 -> -300383 | AP77: 22038.291 | AQ77: =ROUND(AP77,2)*-1 -> -22038.29
A78: INO1 | B78: 1131400006 | E78: 0 | F78: 9002 | G78: Flat | H78: 9002000002 | I78: Buildings & Admin | J78: 1202010202 | L78: Flat (One) (L-4 - Parth CHS)-73 | O78: 1 | P78: EA | Q78: X | S78: 36707 | T78: 43191 | Y78: 2018 | Z78: 800000 | AA78: 01 | AB78: ZSLM | AC78: 11753 | AD78: 32 | AE78: 2 | AG78: =_xlfn.CONCAT(AH78," years ",AI78," days") -> 6 years 277 days | AH78: 6 | AI78: 277 | AJ78: 0 | AK78: 0 | AL78: 800000 | AM78: =ROUND(AL78,2) -> 800000 | AN78: 167923 | AO78: =ROUND(AN78,2)*-1 -> -167923 | AP78: 12320.342 | AQ78: =ROUND(AP78,2)*-1 -> -12320.34
A79: INO1 | B79: 1131400007 | E79: 0 | F79: 9002 | G79: Flat | H79: 9002000003 | I79: Buildings & Admin | J79: 1202010202 | L79: Flat (Three) (L-22, 23, 26 - Parth CHS) -74 | O79: 1 | P79: EA | Q79: X | S79: 36891 | T79: 43191 | Y79: 2018 | Z79: 2700000 | AA79: 01 | AB79: ZSLM | AC79: 11936 | AD79: 32 | AE79: 9 | AG79: =_xlfn.CONCAT(AH79," years ",AI79," days") -> 6 years 277 days | AH79: 6 | AI79: 277 | AJ79: 0 | AK79: 0 | AL79: 2700000 | AM79: =ROUND(AL79,2) -> 2700000 | AN79: 558051 | AO79: =ROUND(AN79,2)*-1 -> -558051 | AP79: 40943.638 | AQ79: =ROUND(AP79,2)*-1 -> -40943.64
A80: INO1 | B80: 1131400164 | E80: 0 | F80: 9002 | G80: Flat | H80: 9002000004 | I80: Buildings & Admin | J80: 1202010202 | L80: 2 Nos. Flat no 17 & 16 Area 16.84 Sq Miters -75 | M80: Purchase | O80: 2 | P80: EA | Q80: X | S80: 38960 | T80: 43191 | Y80: 2018 | Z80: 2900000 | AA80: 01 | AB80: ZSLM | AC80: 14016 | AD80: 38 | AE80: 5 | AG80: =_xlfn.CONCAT(AH80," years ",AI80," days") -> 6 years 277 days | AH80: 6 | AI80: 277 | AJ80: 0 | AK80: 0 | AL80: 2900000 | AM80: =ROUND(AL80,2) -> 2900000 | AN80: 510438 | AO80: =ROUND(AN80,2)*-1 -> -510438 | AP80: 37450.128 | AQ80: =ROUND(AP80,2)*-1 -> -37450.13
A81: INO1 | B81: 1131102149 | E81: 0 | F81: 9002 | G81: Flat | H81: 9002000005 | I81: Buildings & Admin | J81: 1202010202 | L81: Astha Hights-76 | O81: 1 | P81: EA | Q81: X | T81: 43191 | Y81: 1900 | Z81: 1 | AA81: 01 | AB81: ZSLM | AC81: 18078 | AD81: 49 | AE81: 6 | AG81: =_xlfn.CONCAT(AH81," years ",AI81," days") -> 6 years 277 days | AH81: 6 | AI81: 277 | AJ81: 0 | AK81: 0 | AL81: 1 | AM81: =ROUND(AL81,2) -> 1 | AN81: 1 | AO81: =ROUND(AN81,2)*-1 -> -1 | AP81: 0 | AQ81: =ROUND(AP81,2)*-1 -> 0
A82: INO1 | B82: 1191402530 | E82: 0 | F82: 9005 | G82: Freehold Land | H82: 9005000001 | I82: Buildings & Admin | J82: 1202010202 | L82: Land-77 | O82: 1 | P82: EA | Q82: X | S82: 43191 | T82: 43191 | Y82: 2018 | Z82: 47000000 | AA82: 01 | AB82: ZSLM | AC82: 0 | AD82: 0 | AE82: 0 | AG82: =_xlfn.CONCAT(AH82," years ",AI82," days") -> 0 years 0 days | AH82: 0 | AI82: 0 | AJ82: 0 | AK82: 0 | AL82: 47000000 | AM82: =ROUND(AL82,2) -> 47000000 | AN82: 0 | AO82: =ROUND(AN82,2)*-1 -> 0 | AP82: 0 | AQ82: =ROUND(AP82,2)*-1 -> 0
A83: INO1 | B83: 1191403090 | E83: 0 | F83: 9005 | G83: Freehold Land | H83: 9005000002 | I83: Buildings & Admin | J83: 1202010202 | L83: Freehold Land Survey No-215/2/2-78 | O83: 1 | P83: EA | Q83: X | S83: 43775 | T83: 43775 | Y83: 2019 | Z83: 86390500 | AA83: 01 | AB83: ZSLM | AC83: 0 | AD83: 0 | AE83: 0 | AG83: =_xlfn.CONCAT(AH83," years ",AI83," days") -> 0 years 0 days | AH83: 0 | AI83: 0 | AJ83: 0 | AK83: 0 | AL83: 86390500 | AM83: =ROUND(AL83,2) -> 86390500 | AN83: 0 | AO83: =ROUND(AN83,2)*-1 -> 0 | AP83: 0 | AQ83: =ROUND(AP83,2)*-1 -> 0
A84: INO1 | B84: 1101400906 | E84: 0 | F84: 9007 | G84: Factory Equipment & Tools | H84: 9007000001 | I84: Utility | J84: 1202010217 | K84: TPAC/SIL/RO-001 | L84: Ro Plant 5000Lph Bill No. 287/21.1.13 Scale -79 | M84: Guard | O84: 1 | P84: EA | Q84: X | S84: 41297 | T84: 43191 | Y84: 2018 | Z84: 430000 | AA84: 01 | AB84: ZSLM | AC84: 3577 | AD84: 9 | AE84: 10 | AG84: =_xlfn.CONCAT(AH84," years ",AI84," days") -> 6 years 277 days | AH84: 6 | AI84: 277 | AJ84: 0 | AK84: 0 | AL84: 430000 | AM84: =ROUND(AL84,2) -> 430000 | AN84: 296564 | AO84: =ROUND(AN84,2)*-1 -> -296564 | AP84: 21758.617 | AQ84: =ROUND(AP84,2)*-1 -> -21758.62
A85: INO1 | B85: 1101404676 | E85: 0 | F85: 9007 | G85: Factory Equipment & Tools | H85: 9007000002 | I85: Utility | J85: 1202010217 | K85: TPAC/SIL/RO-002 | L85: T/F THROUGH J/V AGST B/NO. GST/SG054/22-23 D-81 | M85: T: 26.04.22 BOOKED FOR PUR RO PLANT 500 LPH VIDE | O85: 1 | P85: EA | Q85: X | S85: 45000 | T85: 45000 | Y85: 2023 | Z85: 2169334.2 | AA85: 01 | AB85: ZSLM | AC85: 3650 | AD85: 10 | AE85: 0 | AG85: =_xlfn.CONCAT(AH85," years ",AI85," days") -> 1 years 293 days | AH85: 1 | AI85: 293 | AJ85: 0 | AK85: 0 | AL85: 2169334.2 | AM85: =ROUND(AL85,2) -> 2169334.2 | AN85: 391074 | AO85: =ROUND(AN85,2)*-1 -> -391074 | AP85: 107575.7 | AQ85: =ROUND(AP85,2)*-1 -> -107575.7
A86: INO1 | B86: 1101101761 | D86: =_xlfn.XLOOKUP(B86,SOM!B:B,SOM!D:D,,0) -> #N/A | E86: 1 | F86: 9007 | G86: Factory Equipment & Tools | H86: 9007000002 | I86: Utility | J86: 1202010217 | L86: Water Purification Ro System 250ltr/hr-82 | O86: 1 | P86: EA | Q86: X | S86: 45618 | T86: 45618 | Y86: 2024 | Z86: 160000 | AA86: 01 | AB86: ZSLM | AC86: 3650 | AD86: 10 | AE86: 0 | AG86: =_xlfn.CONCAT(AH86," years ",AI86," days") -> 0 years 40 days | AH86: 0 | AI86: 40 | AJ86: 0 | AK86: 0 | AL86: 160000 | AM86: =ROUND(AL86,2) -> 160000 | AN86: 86855 | AO86: =ROUND(AN86,2)*-1 -> -86855 | AP86: 7934.6712 | AQ86: =ROUND(AP86,2)*-1 -> -7934.67
A87: INO1 | B87: 1101400341 | E87: 0 | F87: 9007 | G87: Factory Equipment & Tools | H87: 9007000003 | I87: Utility | J87: 1202010217 | K87: CHILLER140TR | L87: Trans Chiller with all accessories-84 | O87: 1 | P87: EA | Q87: X | S87: 39966 | T87: 43191 | Y87: 2018 | Z87: 3325000 | AA87: 01 | AB87: ZSLM | AC87: 2263 | AD87: 6 | AE87: 2 | AG87: =_xlfn.CONCAT(AH87," years ",AI87," days") -> 6 years 73 days | AH87: 6 | AI87: 73 | AJ87: 0 | AK87: 0 | AL87: 3325000 | AM87: =ROUND(AL87,2) -> 3325000 | AN87: 3325000 | AO87: =ROUND(AN87,2)*-1 -> -3325000 | AP87: 0 | AQ87: =ROUND(AP87,2)*-1 -> 0
A88: INO1 | B88: 1101404647 | D88: =_xlfn.XLOOKUP(B88,SOM!B:B,SOM!D:D,,0) -> #N/A | E88: 1 | F88: 9007 | G88: Factory Equipment & Tools | H88: 9007000003 | I88: Utility | J88: 1202010217 | L88: Being Expences towords SS 304 pipe 4 Schedul-85 | M88: e 20 Qty.42nos,Short Elbow 4 schedule 20 Qty.12n | O88: 1 | P88: EA | Q88: X | S88: 44986 | T88: 44986 | Y88: 2023 | Z88: 82374 | AA88: 01 | AB88: ZSLM | AC88: 3650 | AD88: 10 | AE88: 0 | AG88: =_xlfn.CONCAT(AH88," years ",AI88," days") -> 1 years 307 days | AH88: 1 | AI88: 307 | AJ88: 0 | AK88: 0 | AL88: 82374 | AM88: =ROUND(AL88,2) -> 82374 | AN88: 15166 | AO88: =ROUND(AN88,2)*-1 -> -15166 | AP88: 4084.691 | AQ88: =ROUND(AP88,2)*-1 -> -4084.69
A89: INO1 | B89: 1101404922 | D89: =_xlfn.XLOOKUP(B89,SOM!B:B,SOM!D:D,,0) -> #N/A | E89: 2 | F89: 9007 | G89: Factory Equipment & Tools | H89: 9007000003 | I89: Utility | J89: 1202010217 | L89: B/NO. 047 DT: 19.09.23 OF GRACE ENGINEERING -86 | M89: WORKS BOOKED FOR DRYER STAND MAKING FOR 70 DPH M | O89: 1 | P89: EA | Q89: X | S89: 45199 | T89: 45199 | Y89: 2023 | Z89: 24875 | AA89: 01 | AB89: ZSLM | AC89: 3650 | AD89: 10 | AE89: 0 | AG89: =_xlfn.CONCAT(AH89," years ",AI89," days") -> 1 years 94 days | AH89: 1 | AI89: 94 | AJ89: 0 | AK89: 0 | AL89: 24875 | AM89: =ROUND(AL89,2) -> 24875 | AN89: 3128 | AO89: =ROUND(AN89,2)*-1 -> -3128 | AP89: 1233.6438 | AQ89: =ROUND(AP89,2)*-1 -> -1233.64
A90: INO1 | B90: 1101404936 | D90: =_xlfn.XLOOKUP(B90,SOM!B:B,SOM!D:D,,0) -> #N/A | E90: 3 | F90: 9007 | G90: Factory Equipment & Tools | H90: 9007000003 | I90: Utility | J90: 1202010217 | L90: Being purchased MS PIPE VIDE TSGO/23-24/387 -87 | M90: DT: 25.09.23 from Solanki Enterprises and PUR CO | O90: 1 | P90: EA | Q90: X | S90: 45199 | T90: 45199 | Y90: 2023 | Z90: 6695 | AA90: 01 | AB90: ZSLM | AC90: 3650 | AD90: 10 | AE90: 0 | AG90: =_xlfn.CONCAT(AH90," years ",AI90," days") -> 1 years 94 days | AH90: 1 | AI90: 94 | AJ90: 0 | AK90: 0 | AL90: 6695 | AM90: =ROUND(AL90,2) -> 6695 | AN90: 842 | AO90: =ROUND(AN90,2)*-1 -> -842 | AP90: 331.91781 | AQ90: =ROUND(AP90,2)*-1 -> -331.92
A91: INO1 | B91: 1101104016 | D91: =_xlfn.XLOOKUP(B91,SOM!B:B,SOM!D:D,,0) -> #N/A | E91: 4 | F91: 9007 | G91: Factory Equipment & Tools | H91: 9007000003 | I91: Utility | J91: 1202010217 | K91: Chiller 140 TR ( Assesories) | L91: B/NO: 472 DT: 27.1.2022 BEING PURCHASED AS A-88 | M91: LUMINIUM ARMOURED CABLE & COPPER FLEXIBLE CABLE | O91: 202 | P91: EA | Q91: X | S91: 44620 | T91: 44620 | Y91: 2022 | Z91: 503961 | AA91: 01 | AB91: ZSLM | AC91: 3650 | AD91: 10 | AE91: 0 | AG91: =_xlfn.CONCAT(AH91," years ",AI91," days") -> 2 years 308 days | AH91: 2 | AI91: 308 | AJ91: 0 | AK91: 0 | AL91: 503961 | AM91: =ROUND(AL91,2) -> 503961 | AN91: 143318 | AO91: =ROUND(AN91,2)*-1 -> -143318 | AP91: 24991.167 | AQ91: =ROUND(AP91,2)*-1 -> -24991.17
A92: INO1 | B92: 1101400661 | E92: 0 | F92: 9007 | G92: Factory Equipment & Tools | H92: 9007000004 | I92: Utility | J92: 1202010217 | K92: CHILLER170TR + ATB | L92: import 170 TR WATER COOLED SCREW CHILLER ,MO-90 | M92: DEL NO,CRTHD QTY-1, TOTAL COST US $ 43000/-CIF R | O92: 1 | P92: EA | Q92: X | S92: 40817 | T92: 43191 | Y92: 2018 | Z92: 1350000 | AA92: 01 | AB92: ZSLM | AC92: 3103 | AD92: 8 | AE92: 6 | AG92: =_xlfn.CONCAT(AH92," years ",AI92," days") -> 6 years 277 days | AH92: 6 | AI92: 277 | AJ92: 0 | AK92: 0 | AL92: 1350000 | AM92: =ROUND(AL92,2) -> 1350000 | AN92: 1073300 | AO92: =ROUND(AN92,2)*-1 -> -1073300 | AP92: 78746.407 | AQ92: =ROUND(AP92,2)*-1 -> -78746.41
A93: INO1 | B93: 1101405290 | D93: =_xlfn.XLOOKUP(B93,SOM!B:B,SOM!D:D,,0) -> #N/A | E93: 1 | F93: 9007 | G93: Factory Equipment & Tools | H93: 9007000004 | I93: Utility | J93: 1202010217 | K93: Chiller 170 TR ( Assesories) | L93: new chilling water pipe line capitalised-91 | O93: 1 | P93: EA | Q93: X | S93: 45524 | T93: 45524 | Y93: 2024 | Z93: 266656.5 | AA93: 01 | AB93: ZSLM | AC93: 3650 | AD93: 10 | AE93: 0 | AG93: =_xlfn.CONCAT(AH93," years ",AI93," days") -> 0 years 134 days | AH93: 0 | AI93: 134 | AJ93: 0 | AK93: 0 | AL93: 266656.5 | AM93: =ROUND(AL93,2) -> 266656.5 | AN93: 9790 | AO93: =ROUND(AN93,2)*-1 -> -9790 | AP93: 13222.821 | AQ93: =ROUND(AP93,2)*-1 -> -13222.82
A94: INO1 | B94: 1101404540 | E94: 0 | F94: 9007 | G94: Factory Equipment & Tools | H94: 9007000005 | I94: Utility | J94: 1202010217 | K94: CHILLER500TR + ATB (Accessories) | L94: 500TR CENTRIFUGAL CHILLER & ITS ACESSARY.(Ad-93 | M94: dition to New Plant) | O94: 1 | P94: EA | Q94: X | S94: 44910 | T94: 44910 | Y94: 2022 | Z94: 4602270 | AA94: 01 | AB94: ZSLM | AC94: 3650 | AD94: 10 | AE94: 0 | AG94: =_xlfn.CONCAT(AH94," years ",AI94," days") -> 2 years 18 days | AH94: 2 | AI94: 18 | AJ94: 0 | AK94: 0 | AL94: 4602270 | AM94: =ROUND(AL94,2) -> 4602270 | AN94: 943150 | AO94: =ROUND(AN94,2)*-1 -> -943150 | AP94: 228222.29 | AQ94: =ROUND(AP94,2)*-1 -> -228222.29
A95: INO1 | B95: 1101404673 | D95: =_xlfn.XLOOKUP(B95,SOM!B:B,SOM!D:D,,0) -> #N/A | E95: 1 | F95: 9007 | G95: Factory Equipment & Tools | H95: 9007000005 | I95: Utility | J95: 1202010217 | K95: CHILLER500TR + ATB | L95: T/F THROUGH J/V AGST B/NO 8260588 DT: 13.04.-94 | M95: 22 OF BOOKED FOR PUR WATER COOLED CENTRIFUGAL C | O95: 1 | P95: EA | Q95: X | S95: 45000 | T95: 45000 | Y95: 2023 | Z95: 12178087 | AA95: 01 | AB95: ZSLM | AC95: 3650 | AD95: 10 | AE95: 0 | AG95: =_xlfn.CONCAT(AH95," years ",AI95," days") -> 1 years 293 days | AH95: 1 | AI95: 293 | AJ95: 0 | AK95: 0 | AL95: 12178087 | AM95: =ROUND(AL95,2) -> 12178087 | AN95: 2195392 | AO95: =ROUND(AN95,2)*-1 -> -2195392 | AP95: 603899.73 | AQ95: =ROUND(AP95,2)*-1 -> -603899.73
A96: INO1 | B96: 1101405093 | D96: =_xlfn.XLOOKUP(B96,SOM!B:B,SOM!D:D,,0) -> #N/A | E96: 2 | F96: 9007 | G96: Factory Equipment & Tools | H96: 9007000005 | I96: Utility | J96: 1202010217 | L96: BEING T/F THROUGH J/V AGST B/NO. ACPL/131/23-95 | M96: -24 DT: 02.02.24 OF AMICRON CLEANTECH BOOKED FOR | O96: 1080 | P96: EA | Q96: X | S96: 45327 | T96: 45327 | Y96: 2024 | Z96: 206800 | AA96: 01 | AB96: ZSLM | AC96: 3650 | AD96: 10 | AE96: 0 | AG96: =_xlfn.CONCAT(AH96," years ",AI96," days") -> 0 years 331 days | AH96: 0 | AI96: 331 | AJ96: 0 | AK96: 0 | AL96: 206800 | AM96: =ROUND(AL96,2) -> 206800 | AN96: 18754 | AO96: =ROUND(AN96,2)*-1 -> -18754 | AP96: 10254.658 | AQ96: =ROUND(AP96,2)*-1 -> -10254.66
A97: INO1 | B97: 1101104040 | D97: =_xlfn.XLOOKUP(B97,SOM!B:B,SOM!D:D,,0) -> #N/A | E97: 3 | F97: 9007 | G97: Factory Equipment & Tools | H97: 9007000005 | I97: Utility | J97: 1202010217 | L97: Being Booked for charges towards Comissionin-96 | M97: g for 1 no Trane chiller from Trane Technologies | O97: 1 | P97: EA | Q97: X | S97: 44622 | T97: 44622 | Y97: 2022 | Z97: 87000 | AA97: 01 | AB97: ZSLM | AC97: 3650 | AD97: 10 | AE97: 0 | AG97: =_xlfn.CONCAT(AH97," years ",AI97," days") -> 2 years 306 days | AH97: 2 | AI97: 306 | AJ97: 0 | AK97: 0 | AL97: 87000 | AM97: =ROUND(AL97,2) -> 87000 | AN97: 24694 | AO97: =ROUND(AN97,2)*-1 -> -24694 | AP97: 4313.9452 | AQ97: =ROUND(AP97,2)*-1 -> -4313.95
A98: INO1 | B98: 1101400916 | E98: 0 | F98: 9007 | G98: Factory Equipment & Tools | H98: 9007000006 | I98: Utility | J98: 1202010217 | K98: PHE -05 (ALFA LAVEL) PHE -06 (ALFA LAVEL) | L98: Plate Heat Exchanger Tl 10 Pfm With 152 Plat-98 | M98: es-2 Pcs.Agst.Bno:8 Dt:21.01.13 From Pastan Engi | O98: 1 | P98: EA | Q98: X | S98: 41303 | T98: 43191 | Y98: 2018 | Z98: 650000 | AA98: 01 | AB98: ZSLM | AC98: 3577 | AD98: 9 | AE98: 10 | AG98: =_xlfn.CONCAT(AH98," years ",AI98," days") -> 6 years 277 days | AH98: 6 | AI98: 277 | AJ98: 0 | AK98: 0 | AL98: 650000 | AM98: =ROUND(AL98,2) -> 650000 | AN98: 448295 | AO98: =ROUND(AN98,2)*-1 -> -448295 | AP98: 32890.351 | AQ98: =ROUND(AP98,2)*-1 -> -32890.35
A99: INO1 | B99: 1101401778 | E99: 0 | F99: 9007 | G99: Factory Equipment & Tools | H99: 9007000007 | I99: Utility | J99: 1202010217 | K99: PHE -04 (ALFA LAVEL) | L99: Plate Heat Exchanger TL 10PFM with 155 Plate-100 | M99: s | O99: 1 | P99: EA | Q99: X | S99: 42323 | T99: 43191 | Y99: 2018 | Z99: 420000 | AA99: 01 | AB99: ZSLM | AC99: 4563 | AD99: 12 | AE99: 6 | AG99: =_xlfn.CONCAT(AH99," years ",AI99," days") -> 6 years 277 days | AH99: 6 | AI99: 277 | AJ99: 0 | AK99: 0 | AL99: 420000 | AM99: =ROUND(AL99,2) -> 420000 | AN99: 227074 | AO99: =ROUND(AN99,2)*-1 -> -227074 | AP99: 16660.385 | AQ99: =ROUND(AP99,2)*-1 -> -16660.39
A100: INO1 | B100: 1101400923 | E100: 0 | F100: 9007 | G100: Factory Equipment & Tools | H100: 9007000008 | I100: Utility | J100: 1202010217 | L100: Grundfos Make Pump Crcm 64-2 & Nb 125-250/24-102 | M100: 8 Cooling Tower Agst.Bno:260 Dt:30.01.2013 From | O100: 1 | P100: EA | Q100: X | S100: 41307 | T100: 43191 | Y100: 2018 | Z100: 215000 | AA100: 01 | AB100: ZSLM | AC100: 1752 | AD100: 4 | AE100: 10 | AG100: =_xlfn.CONCAT(AH100," years ",AI100," days") -> 4 years 292 days | AH100: 4 | AI100: 292 | AJ100: 0 | AK100: 0 | AL100: 215000 | AM100: =ROUND(AL100,2) -> 215000 | AN100: 215000 | AO100: =ROUND(AN100,2)*-1 -> -215000 | AP100: 0 | AQ100: =ROUND(AP100,2)*-1 -> 0
A101: INO1 | B101: 1101404553 | D101: =_xlfn.XLOOKUP(B101,SOM!B:B,SOM!D:D,,0) -> #N/A | E101: 1 | F101: 9007 | G101: Factory Equipment & Tools | H101: 9007000008 | I101: Utility | J101: 1202010217 | K101: COOLING WATER SEC. PRO. PUMP-01 TO 06, CHILLING WATER SEC. PRO. PUMP-01 TO 07, PHE PRIMERY PROCESS PUMP-01 TO 03, CHILLER PRIMERY PROCESS PUMP-01 TO 03, TPAC/SIL/COOLING TOWER-02 & 03, PHE -01 TO 03 (ALFA LAVEL) | L101: B/NO : GST/356/21-22 DT.17.01.22 OF SCALE GU-103 | M101: ARD BOOKED FOR PURGRUNDFOS PUMP VIDE TSGO/21-22/ | O101: 1 | P101: EA | Q101: X | S101: 44910 | T101: 44910 | Y101: 2022 | Z101: 7877130.2 | AA101: 01 | AB101: ZSLM | AC101: 3650 | AD101: 10 | AE101: 0 | AG101: =_xlfn.CONCAT(AH101," years ",AI101," days") -> 2 years 18 days | AH101: 2 | AI101: 18 | AJ101: 0 | AK101: 0 | AL101: 7877130.2 | AM101: =ROUND(AL101,2) -> 7877130.2 | AN101: 1614272 | AO101: =ROUND(AN101,2)*-1 -> -1614272 | AP101: 390619.48 | AQ101: =ROUND(AP101,2)*-1 -> -390619.48
A102: INO1 | B102: 1101404680 | D102: =_xlfn.XLOOKUP(B102,SOM!B:B,SOM!D:D,,0) -> #N/A | E102: 2 | F102: 9007 | G102: Factory Equipment & Tools | H102: 9007000008 | I102: Utility | J102: 1202010217 | K102: Clloing Tower Pipe Line | L102: SS SEAMLESS ,SS ERW,PPR PIPE & FITTINGS INC-104 | M102: LUDING INSULATION (All Pipe Lines)(Addition to N | O102: 1 | P102: EA | Q102: X | S102: 45000 | T102: 45000 | Y102: 2023 | Z102: 4196003.7 | AA102: 01 | AB102: ZSLM | AC102: 3650 | AD102: 10 | AE102: 0 | AG102: =_xlfn.CONCAT(AH102," years ",AI102," days") -> 1 years 293 days | AH102: 1 | AI102: 293 | AJ102: 0 | AK102: 0 | AL102: 4196003.7 | AM102: =ROUND(AL102,2) -> 4196003.7 | AN102: 756430 | AO102: =ROUND(AN102,2)*-1 -> -756430 | AP102: 208076.06 | AQ102: =ROUND(AP102,2)*-1 -> -208076.06
A103: INO1 | B103: 1101405165 | D103: =_xlfn.XLOOKUP(B103,SOM!B:B,SOM!D:D,,0) -> #N/A | E103: 3 | F103: 9007 | G103: Factory Equipment & Tools | H103: 9007000008 | I103: Utility | J103: 1202010217 | K103: CHILLER Primary Pump 1 | L103: B/NO. EPL/2023-24/167 DTD: 30.03.24 OF ENERP-105 | M103: RONE BOOKED FOR PUR 15 KW CHILLER PUMP VIDE TSGO | O103: 4 | P103: EA | Q103: X | S103: 45402 | T103: 45402 | Y103: 2024 | Z103: 668360 | AA103: 01 | AB103: ZSLM | AC103: 3650 | AD103: 10 | AE103: 0 | AG103: =_xlfn.CONCAT(AH103," years ",AI103," days") -> 0 years 256 days | AH103: 0 | AI103: 256 | AJ103: 0 | AK103: 0 | AL103: 668360 | AM103: =ROUND(AL103,2) -> 668360 | AN103: 46877 | AO103: =ROUND(AN103,2)*-1 -> -46877 | AP103: 33143.088 | AQ103: =ROUND(AP103,2)*-1 -> -33143.09
A104: INO1 | B104: 1101100498 | D104: =_xlfn.XLOOKUP(B104,SOM!B:B,SOM!D:D,,0) -> #N/A | E104: 4 | F104: 9007 | G104: Factory Equipment & Tools | H104: 9007000008 | I104: Utility | J104: 1202010217 | L104: Cooling Tower-106 | O104: 1 | P104: EA | Q104: X | S104: 40446 | T104: 43191 | Y104: 2018 | Z104: 220000 | AA104: 01 | AB104: ZSLM | AC104: 2738 | AD104: 7 | AE104: 6 | AG104: =_xlfn.CONCAT(AH104," years ",AI104," days") -> 6 years 277 days | AH104: 6 | AI104: 277 | AJ104: 0 | AK104: 0 | AL104: 220000 | AM104: =ROUND(AL104,2) -> 220000 | AN104: 198225 | AO104: =ROUND(AN104,2)*-1 -> -198225 | AP104: 14543.444 | AQ104: =ROUND(AP104,2)*-1 -> -14543.44
A105: INO1 | B105: 1101504332 | D105: =_xlfn.XLOOKUP(B105,SOM!B:B,SOM!D:D,,0) -> #N/A | E105: 5 | F105: 9007 | G105: Factory Equipment & Tools | H105: 9007000008 | I105: Utility | J105: 1202010217 | L105: Grundfos Chilled water Pump for Cooling Towe-107 | M105: r Model no NB-50-200/181 | O105: 1 | P105: EA | Q105: X | S105: 44865 | T105: 44865 | Y105: 2022 | Z105: 115000 | AA105: 01 | AB105: ZSLM | AC105: 3650 | AD105: 10 | AE105: 0 | AG105: =_xlfn.CONCAT(AH105," years ",AI105," days") -> 2 years 63 days | AH105: 2 | AI105: 63 | AJ105: 0 | AK105: 0 | AL105: 115000 | AM105: =ROUND(AL105,2) -> 115000 | AN105: 106013 | AO105: =ROUND(AN105,2)*-1 -> -106013 | AP105: 5702.9055 | AQ105: =ROUND(AP105,2)*-1 -> -5702.91
A106: INO1 | B106: 1101504335 | D106: =_xlfn.XLOOKUP(B106,SOM!B:B,SOM!D:D,,0) -> #N/A | E106: 6 | F106: 9007 | G106: Factory Equipment & Tools | H106: 9007000008 | I106: Utility | J106: 1202010217 | L106: Supply of Grundfos Make Pump Model no NB 40--108 | M106: 160/144 | O106: 1 | P106: EA | Q106: X | S106: 44865 | T106: 44865 | Y106: 2022 | Z106: 62500 | AA106: 01 | AB106: ZSLM | AC106: 3650 | AD106: 10 | AE106: 0 | AG106: =_xlfn.CONCAT(AH106," years ",AI106," days") -> 2 years 63 days | AH106: 2 | AI106: 63 | AJ106: 0 | AK106: 0 | AL106: 62500 | AM106: =ROUND(AL106,2) -> 62500 | AN106: 57616 | AO106: =ROUND(AN106,2)*-1 -> -57616 | AP106: 3099.1661 | AQ106: =ROUND(AP106,2)*-1 -> -3099.17
A107: INO1 | B107: 1101403333 | E107: 0 | F107: 9007 | G107: Factory Equipment & Tools | H107: 9007000009 | I107: Utility | J107: 1202010217 | K107: TPAC/SIL/HPAD-001 | L107: Being Compressed air dryer high pressure 300-110 | M107: cfm 40 to 42 bar G . Air dryer cooled . R134A p | O107: 1 | P107: EA | Q107: X | S107: 44020 | T107: 44020 | Y107: 2020 | Z107: 232250 | AA107: 01 | AB107: ZSLM | AC107: 3650 | AD107: 10 | AE107: 0 | AG107: =_xlfn.CONCAT(AH107," years ",AI107," days") -> 4 years 178 days | AH107: 4 | AI107: 178 | AJ107: 0 | AK107: 0 | AL107: 232250 | AM107: =ROUND(AL107,2) -> 232250 | AN107: 104226 | AO107: =ROUND(AN107,2)*-1 -> -104226 | AP107: 11517.219 | AQ107: =ROUND(AP107,2)*-1 -> -11517.22
A108: INO1 | B108: 1101404036 | D108: =_xlfn.XLOOKUP(B108,SOM!B:B,SOM!D:D,,0) -> #N/A | E108: 1 | F108: 9007 | G108: Factory Equipment & Tools | H108: 9007000009 | I108: Utility | J108: 1202010217 | K108: TPAC/SIL/HP-001 | L108: Being COMPRESSOR BLOCK-P10(LOCAL P/R) pur fr-111 | M108: om Chicago Pneumatic Compressors vide inv no FO2 | O108: 1 | P108: EA | Q108: X | S108: 44621 | T108: 44621 | Y108: 2022 | Z108: 1622288 | AA108: 01 | AB108: ZSLM | AC108: 3650 | AD108: 10 | AE108: 0 | AG108: =_xlfn.CONCAT(AH108," years ",AI108," days") -> 2 years 307 days | AH108: 2 | AI108: 307 | AJ108: 0 | AK108: 0 | AL108: 1622288 | AM108: =ROUND(AL108,2) -> 1622288 | AN108: 460908 | AO108: =ROUND(AN108,2)*-1 -> -460908 | AP108: 80447.283 | AQ108: =ROUND(AP108,2)*-1 -> -80447.28
A109: INO1 | B109: 1101405073 | D109: =_xlfn.XLOOKUP(B109,SOM!B:B,SOM!D:D,,0) -> #N/A | E109: 2 | F109: 9007 | G109: Factory Equipment & Tools | H109: 9007000009 | I109: Utility | J109: 1202010217 | L109: BEING T/F THROUGH J/V AGST B/NO. 070 DT: 18.-112 | M109: 01.24 OF GRACE ENGINEERING WORKS BOOKED FOR CHIL | O109: 1 | P109: EA | Q109: X | S109: 45310 | T109: 45310 | Y109: 2024 | Z109: 48353 | AA109: 01 | AB109: ZSLM | AC109: 3650 | AD109: 10 | AE109: 0 | AG109: =_xlfn.CONCAT(AH109," years ",AI109," days") -> 0 years 348 days | AH109: 0 | AI109: 348 | AJ109: 0 | AK109: 0 | AL109: 48353 | AM109: =ROUND(AL109,2) -> 48353 | AN109: 4610 | AO109: =ROUND(AN109,2)*-1 -> -4610 | AP109: 2397.8732 | AQ109: =ROUND(AP109,2)*-1 -> -2397.87
A110: INO1 | B110: 1101400374 | E110: 0 | F110: 9007 | G110: Factory Equipment & Tools | H110: 9007000010 | I110: Utility | J110: 1202010217 | K110: TPAC/SIL/HP-002 & HPAD 2 | L110: Air Compressor-Chicago Phenu-114 | O110: 1 | P110: EA | Q110: X | S110: 40089 | T110: 43191 | Y110: 2018 | Z110: 480000 | AA110: 01 | AB110: ZSLM | AC110: 548 | AD110: 1 | AE110: 6 | AG110: =_xlfn.CONCAT(AH110," years ",AI110," days") -> 1 years 183 days | AH110: 1 | AI110: 183 | AJ110: 0 | AK110: 0 | AL110: 480000 | AM110: =ROUND(AL110,2) -> 480000 | AN110: 480000 | AO110: =ROUND(AN110,2)*-1 -> -480000 | AP110: 0 | AQ110: =ROUND(AP110,2)*-1 -> 0
A111: INO1 | B111: 1101400525 | E111: 0 | F111: 9007 | G111: Factory Equipment & Tools | H111: 9007000011 | I111: Utility | J111: 1202010217 | K111: TPAC/SIL/HP-003 & HPAD 3 | L111: Oil Free Air Pet Compressor-Big-116 | O111: 1 | P111: EA | Q111: X | S111: 40492 | T111: 43191 | Y111: 2018 | Z111: 730000 | AA111: 01 | AB111: ZSLM | AC111: 949 | AD111: 2 | AE111: 7 | AG111: =_xlfn.CONCAT(AH111," years ",AI111," days") -> 2 years 219 days | AH111: 2 | AI111: 219 | AJ111: 0 | AK111: 0 | AL111: 730000 | AM111: =ROUND(AL111,2) -> 730000 | AN111: 730000 | AO111: =ROUND(AN111,2)*-1 -> -730000 | AP111: 0 | AQ111: =ROUND(AP111,2)*-1 -> 0
A112: INO1 | B112: 1101400613 | E112: 0 | F112: 9007 | G112: Factory Equipment & Tools | H112: 9007000012 | I112: Utility | J112: 1202010217 | K112: TPAC/SIL/HP-004 | L112: Oil Free Air Pet Compressor-118 | O112: 1 | P112: EA | Q112: X | S112: 40679 | T112: 43191 | Y112: 2018 | Z112: 740000 | AA112: 01 | AB112: ZSLM | AC112: 1132 | AD112: 3 | AE112: 1 | AG112: =_xlfn.CONCAT(AH112," years ",AI112," days") -> 3 years 37 days | AH112: 3 | AI112: 37 | AJ112: 0 | AK112: 0 | AL112: 740000 | AM112: =ROUND(AL112,2) -> 740000 | AN112: 740000 | AO112: =ROUND(AN112,2)*-1 -> -740000 | AP112: 0 | AQ112: =ROUND(AP112,2)*-1 -> 0
A113: INO1 | B113: 1101403697 | D113: =_xlfn.XLOOKUP(B113,SOM!B:B,SOM!D:D,,0) -> #N/A | E113: 1 | F113: 9007 | G113: Factory Equipment & Tools | H113: 9007000012 | I113: Utility | J113: 1202010217 | K113: TPAC/SIL/HPAD-004 | L113: Being Compressed air dryer high pressure 300-119 | M113: cfm 40 to 42 bar G air cooled R134A pur from Gem | O113: 1 | P113: EA | Q113: X | S113: 44336 | T113: 44336 | Y113: 2021 | Z113: 164664 | AA113: 01 | AB113: ZSLM | AC113: 3650 | AD113: 10 | AE113: 0 | AG113: =_xlfn.CONCAT(AH113," years ",AI113," days") -> 3 years 227 days | AH113: 3 | AI113: 227 | AJ113: 0 | AK113: 0 | AL113: 164664 | AM113: =ROUND(AL113,2) -> 164664 | AN113: 59640 | AO113: =ROUND(AN113,2)*-1 -> -59640 | AP113: 8165.4773 | AQ113: =ROUND(AP113,2)*-1 -> -8165.48
A114: INO1 | B114: 1101404755 | D114: =_xlfn.XLOOKUP(B114,SOM!B:B,SOM!D:D,,0) -> #N/A | E114: 2 | F114: 9007 | G114: Factory Equipment & Tools | H114: 9007000012 | I114: Utility | J114: 1202010217 | L114: BEING T/F THROUGH J/V AGST B/NO. T/23-24/015-120 | M114: DT: 09.05.23 OF PACE AFTERMARKET BOOKED FOR PUR | O114: 4 | P114: EA | Q114: X | S114: 45064 | T114: 45064 | Y114: 2023 | Z114: 247080 | AA114: 01 | AB114: ZSLM | AC114: 3650 | AD114: 10 | AE114: 0 | AG114: =_xlfn.CONCAT(AH114," years ",AI114," days") -> 1 years 229 days | AH114: 1 | AI114: 229 | AJ114: 0 | AK114: 0 | AL114: 247080 | AM114: =ROUND(AL114,2) -> 247080 | AN114: 40210 | AO114: =ROUND(AN114,2)*-1 -> -40210 | AP114: 12252.192 | AQ114: =ROUND(AP114,2)*-1 -> -12252.19
A115: INO1 | B115: 1101404799 | D115: =_xlfn.XLOOKUP(B115,SOM!B:B,SOM!D:D,,0) -> #N/A | E115: 3 | F115: 9007 | G115: Factory Equipment & Tools | H115: 9007000012 | I115: Utility | J115: 1202010217 | L115: B/NO. 031 DT: 15.06.23 OF GRACE ENGINEERING -121 | M115: BOOKED FOR AIRLINE MAKING FOR NEW MOULD ROOM IN | O115: 1 | P115: EA | Q115: X | S115: 45108 | T115: 45108 | Y115: 2023 | Z115: 56781 | AA115: 01 | AB115: ZSLM | AC115: 3650 | AD115: 10 | AE115: 0 | AG115: =_xlfn.CONCAT(AH115," years ",AI115," days") -> 1 years 185 days | AH115: 1 | AI115: 185 | AJ115: 0 | AK115: 0 | AL115: 56781 | AM115: =ROUND(AL115,2) -> 56781 | AN115: 8556 | AO115: =ROUND(AN115,2)*-1 -> -8556 | AP115: 2815.7564 | AQ115: =ROUND(AP115,2)*-1 -> -2815.76
A116: INO1 | B116: 1101504320 | E116: 0 | F116: 9007 | G116: Factory Equipment & Tools | H116: 9007000013 | I116: Utility | J116: 1202010217 | K116: TPAC/SIL/HP-005, TPAC/SIL/HPAD-005 | L116: Compressor AIR DRYER-123 | O116: 1 | P116: EA | Q116: X | S116: 44865 | T116: 44865 | Y116: 2022 | Z116: 400000 | AA116: 01 | AB116: ZSLM | AC116: 3650 | AD116: 10 | AE116: 0 | AG116: =_xlfn.CONCAT(AH116," years ",AI116," days") -> 2 years 63 days | AH116: 2 | AI116: 63 | AJ116: 0 | AK116: 0 | AL116: 400000 | AM116: =ROUND(AL116,2) -> 400000 | AN116: 270137 | AO116: =ROUND(AN116,2)*-1 -> -270137 | AP116: 19835.603 | AQ116: =ROUND(AP116,2)*-1 -> -19835.6
A117: INO1 | B117: 1101404871 | D117: =_xlfn.XLOOKUP(B117,SOM!B:B,SOM!D:D,,0) -> #N/A | E117: 1 | F117: 9007 | G117: Factory Equipment & Tools | H117: 9007000013 | I117: Utility | J117: 1202010217 | L117: BEING T/F THROUGH J/V AGST B/NO. 23-324/2981-124 | M117: DT: 18.08.23 OF SAINATH STRUCTURES BOOKED FOR P | O117: 401 | P117: EA | Q117: X | S117: 45167 | T117: 45167 | Y117: 2023 | Z117: 24149.5 | AA117: 01 | AB117: ZSLM | AC117: 3650 | AD117: 10 | AE117: 0 | AG117: =_xlfn.CONCAT(AH117," years ",AI117," days") -> 1 years 126 days | AH117: 1 | AI117: 126 | AJ117: 0 | AK117: 0 | AL117: 24149.5 | AM117: =ROUND(AL117,2) -> 24149.5 | AN117: 3249 | AO117: =ROUND(AN117,2)*-1 -> -3249 | AP117: 1197.1545 | AQ117: =ROUND(AP117,2)*-1 -> -1197.15
A118: INO1 | B118: 1101504267 | E118: 0 | F118: 9007 | G118: Factory Equipment & Tools | H118: 9007000014 | I118: Utility | J118: 1202010217 | K118: TPAC/SIL/HP-006, TPAC/SIL/HPAD-006 | L118: CP AIR COMPRESSOR with all Accessories-126 | O118: 1 | P118: EA | Q118: X | S118: 44845 | T118: 44845 | Y118: 2022 | Z118: 510000 | AA118: 01 | AB118: ZSLM | AC118: 3650 | AD118: 10 | AE118: 0 | AG118: =_xlfn.CONCAT(AH118," years ",AI118," days") -> 2 years 83 days | AH118: 2 | AI118: 83 | AJ118: 0 | AK118: 0 | AL118: 510000 | AM118: =ROUND(AL118,2) -> 510000 | AN118: 510000 | AO118: =ROUND(AN118,2)*-1 -> -510000 | AP118: 0 | AQ118: =ROUND(AP118,2)*-1 -> 0
...

Sheet SOM
A1: Company Code | B1: External/Legacy Asset Number* External/legacy asset ID. It is an unique number that identifies a fixed asset in the Legacy System. Please note: In S/4HANA Cloud only INTERNAL number assignment is supported. The legacy asset number is migrated to the field "Original Asset" in the tab "Origin" for reference. Key fields are mandatory and must always be filled with a unique key. If there is internal numbering, you can provide the key of your source system or any other unique key. The key is technically mandatory for the tool to internally connect the records of subordinated sheets with the records of the superordinated sheets. Type: Text Length: 12 | C1: Asset number | D1: Main Asset Legacy Number | E1: Asset Subnumber* Must be "0", when migrating a MAIN asset source file. Must be a sequential number (unequal "0"), when migrating an asset subnumber source file (max. 4-digits). The asset subnumber is migrated to the field "Original Asset Subnumber" in the tab "Origin" for reference. This is the number which, together with the main asset number, uniquely identifies a fixed asset in Asset Accounting. Using the asset sub-number, you can: - Provide for separate management of later acquisitions to assets. - Represent complex fixed assets with their component parts. Type: Text Length: 4 | F1: Asset Class in SAP | G1: Asset Class in SAP | I1: PM Sheet Maped Cost Center | J1: Cost Center Code | K1: Equipment ID | L1: Asset Description* Asset Description Type: Text Length: 50 | M1: Asset Description 2 Additional Asset description. Type: Text Length: 50 | N1: Serial Number You can enter the manufacturer's serial number in this field. Type: Text Length: 18 | O1: Quantity Quantity Type: Number Length: 13 Decimal: 3 | P1: Base Unit of Measure Base Unit of Measure, for example: KG, KM, TON... Type: Text Length: 80 | Q1: Asset is managed historically Set this indicator to 'X', if the asset is managed historically. Type: Text Length: 1 | R1: Asset Main Number Text In this field, you can enter any desired name for an asset main number. The text is then used, for example, in reporting, and in the display values transaction when accessing totals per asset main number. Type: Text Length: 50 | S1: Original Purchase Date | T1: Asset Capitalization Date* Reference date of the posting that leads to asset being capitalized. Type: Date | U1: Deactivation Date Asset value date of the retirement posting for a full retirement in this field. Type: Date | V1: Plant The Plant is mandatory for migrating an Asset Location. Without indicating the Plant the Asset Location cannot be determined. Type: Text Length: 80 | W1: Asset Location Migrating an Asset Location, the indication of the Plant is mandatory. Without a plant the Asset Location cannot be determined. Type: Text Length: 80 | X1: License Plate No. of Vehicle You can enter the license plate number for a vehicle here. Your entry is saved as time-dependent data, so that a history is created when there is a change in the license plate number. Type: Text Length: 15 | Y1: Fiscal Year of Original Acquisition Fiscal year in which the asset was originally acquired (before the asset transfer). This field is not automatically filled; you need to supply it. Type: Number Length: 4 | Z1: Original Acquisition Value Acquisition value of the asset before the asset transfer. This field is not automatically filled; you need to supply it. Type: Number Length: 23 Decimal: 2 | AA1: Depreciation Area* Depreciation area, which is managed in the system as a real depreciation area (not a derived depreciation area). Type: Text Length: 80 | AB1: Depreciation Key* Depreciation keys are defined at the level of the chart of depreciation. Type: Text Length: 80 | AC1: Life of Assets as per Co's Act | AD1: Useful Life (in years) The two fields ‘Useful Life (in years)’ and ‘Useful Life (in periods)’ are additive. For example, a useful life of 3.5 years would be maintained as ‘Useful Life (in years)’ = 3 and ‘Useful Life (in periods)’ = 6. Type: Number Length: 3 | AE1: Useful Life (in periods) The two fields ‘Useful Life (in years)’ and ‘Useful Life (in periods)’ are additive. For example, a useful life of 3.5 years would be maintained as ‘Useful Life (in years)’ = 3 and ‘Useful Life (in periods)’ = 6. Type: Number Length: 3 | AF1: Used life | AG1: Exp. usef. life in years at start of FY The portion of the useful life of the asset that has already expired. Type: Number Length: 3 | AH1: Exp. usef. life in perio. at start of FY The portion of the useful life of the asset that has already expired. Type: Number Length: 3 | AI1: Cumulated Acquisition Value Please enter one row for each depreciation area. Type: Number Length: 23 Decimal: 2 | AJ1: Accumulated Ordinary Depreciation Must be negative, e.g. -1267,00, in most of the business cases. Type: Number Length: 23 Decimal: 2 | AK1: Current Fiscal Year* Current fiscal year = active fiscal year in system. Period, 12 as a rule, for which the company is to create its inventory and balance sheet. The fiscal year can be the same as the calendar year, but does not have to be. Type: Number Length: 4 | AL1: Posted Ordinary Deprec. for the Year Depreciation values must be negative, e.g. -1234,56 and corrections of depreciation values positve, e.g. 1234,56. Type: Number Length: 23 Decimal: 2
A2: IN01 | B2: 1131100078 | E2: 0 | F2: Factory Building | G2: 9001 | H2: 9001000001 | I2: Buildings & Admin | J2: 1202010202 | L2: Factory Building-8 | O2: 1 | P2: EA | Q2: X | S2: 38078 | T2: 43340 | Y2: 2018 | Z2: 22874756 | AA2: 01 | AB2: ZSLM | AC2: 5694 | AD2: 15 | AE2: 7 | AF2: =_xlfn.CONCAT(AG2," years ",AH2," days") -> 6 years 128 days | AG2: 6 | AH2: 128 | AI2: 22874756 | AJ2: 9308186 | AK2: 2025 | AL2: 727138.98
A3: IN01 | B3: 1131100083 | E3: 0 | F3: Factory Building | G3: 9001 | H3: 9001000001 | I3: Buildings & Admin | J3: 1202010202 | L3: Factory Building-9 | O3: 1 | P3: EA | Q3: X | S3: 38107 | T3: 43340 | Y3: 2018 | Z3: 131423.56 | AA3: 01 | AB3: ZSLM | AC3: 5731 | AD3: 15 | AE3: 9 | AF3: =_xlfn.CONCAT(AG3," years ",AH3," days") -> 6 years 128 days | AG3: 6 | AH3: 128 | AI3: 131423.56 | AJ3: 53134 | AK3: 2025 | AL3: 4150.3813
A4: IN01 | B4: 1131100087 | E4: 0 | F4: Factory Building | G4: 9001 | H4: 9001000001 | I4: Buildings & Admin | J4: 1202010202 | L4: Factory Building-10 | O4: 1 | P4: EA | Q4: X | S4: 38138 | T4: 43340 | Y4: 2018 | Z4: 385260.71 | AA4: 01 | AB4: ZSLM | AC4: 5767 | AD4: 15 | AE4: 10 | AF4: =_xlfn.CONCAT(AG4," years ",AH4," days") -> 6 years 128 days | AG4: 6 | AH4: 128 | AI4: 385260.71 | AJ4: 154786 | AK4: 2025 | AL4: 12091.36
A5: IN01 | B5: 1131100092 | E5: 0 | F5: Factory Building | G5: 9001 | H5: 9001000001 | I5: Buildings & Admin | J5: 1202010202 | L5: Factory Building-11 | O5: 1 | P5: EA | Q5: X | S5: 38168 | T5: 43340 | Y5: 2018 | Z5: 104811.22 | AA5: 01 | AB5: ZSLM | AC5: 5767 | AD5: 15 | AE5: 10 | AF5: =_xlfn.CONCAT(AG5," years ",AH5," days") -> 6 years 128 days | AG5: 6 | AH5: 128 | AI5: 104811.22 | AJ5: 42110 | AK5: 2025 | AL5: 3289.3506
A6: IN01 | B6: 1131100094 | E6: 0 | F6: Factory Building | G6: 9001 | H6: 9001000001 | I6: Buildings & Admin | J6: 1202010202 | L6: Factory Building-12 | O6: 1 | P6: EA | Q6: X | S6: 38220 | T6: 43340 | Y6: 2018 | Z6: 525906 | AA6: 01 | AB6: ZSLM | AC6: 5840 | AD6: 16 | AE6: 0 | AF6: =_xlfn.CONCAT(AG6," years ",AH6," days") -> 6 years 128 days | AG6: 6 | AH6: 128 | AI6: 525906 | AJ6: 208651 | AK6: 2025 | AL6: 16299.888
A7: IN01 | B7: 1131100100 | E7: 0 | F7: Factory Building | G7: 9001 | H7: 9001000001 | I7: Buildings & Admin | J7: 1202010202 | L7: Factory Building-13 | O7: 1 | P7: EA | Q7: X | S7: 38260 | T7: 43340 | Y7: 2018 | Z7: 522189.82 | AA7: 01 | AB7: ZSLM | AC7: 5877 | AD7: 16 | AE7: 1 | AF7: =_xlfn.CONCAT(AG7," years ",AH7," days") -> 6 years 128 days | AG7: 6 | AH7: 128 | AI7: 522189.82 | AJ7: 205873 | AK7: 2025 | AL7: 16082.16
A8: IN01 | B8: 1131100110 | E8: 0 | F8: Factory Building | G8: 9001 | H8: 9001000001 | I8: Buildings & Admin | J8: 1202010202 | L8: Factory Building-14 | O8: 1 | P8: EA | Q8: X | S8: 38352 | T8: 43340 | Y8: 2018 | Z8: 161919.78 | AA8: 01 | AB8: ZSLM | AC8: 5950 | AD8: 16 | AE8: 4 | AF8: =_xlfn.CONCAT(AG8," years ",AH8," days") -> 6 years 128 days | AG8: 6 | AH8: 128 | AI8: 161919.78 | AJ8: 63054 | AK8: 2025 | AL8: 4925.1562
A9: IN01 | B9: 1131100116 | E9: 0 | F9: Factory Building | G9: 9001 | H9: 9001000001 | I9: Buildings & Admin | J9: 1202010202 | L9: Factory Building-15 | O9: 1 | P9: EA | Q9: X | S9: 38383 | T9: 43340 | Y9: 2018 | Z9: 114680.74 | AA9: 01 | AB9: ZSLM | AC9: 5986 | AD9: 16 | AE9: 5 | AF9: =_xlfn.CONCAT(AG9," years ",AH9," days") -> 6 years 128 days | AG9: 6 | AH9: 128 | AI9: 114680.74 | AJ9: 44390 | AK9: 2025 | AL9: 3467.1538
A10: IN01 | B10: 1131100119 | E10: 0 | F10: Factory Building | G10: 9001 | H10: 9001000001 | I10: Buildings & Admin | J10: 1202010202 | L10: Factory Building-16 | O10: 1 | P10: EA | Q10: X | S10: 38411 | T10: 43340 | Y10: 2018 | Z10: 632764.31 | AA10: 01 | AB10: ZSLM | AC10: 6023 | AD10: 16 | AE10: 6 | AF10: =_xlfn.CONCAT(AG10," years ",AH10," days") -> 6 years 128 days | AG10: 6 | AH10: 128 | AI10: 632764.31 | AJ10: 243419 | AK10: 2025 | AL10: 19015.788
A11: IN01 | B11: 1131100122 | E11: 0 | F11: Factory Building | G11: 9001 | H11: 9001000001 | I11: Buildings & Admin | J11: 1202010202 | L11: Factory Building-17 | O11: 1 | P11: EA | Q11: X | S11: 38442 | T11: 43340 | Y11: 2018 | Z11: 536344.26 | AA11: 01 | AB11: ZSLM | AC11: 6059 | AD11: 16 | AE11: 7 | AF11: =_xlfn.CONCAT(AG11," years ",AH11," days") -> 6 years 128 days | AG11: 6 | AH11: 128 | AI11: 536344.26 | AJ11: 205101 | AK11: 2025 | AL11: 16022.54
A12: IN01 | B12: 1131100400 | E12: 0 | F12: Factory Building | G12: 9001 | H12: 9001000001 | I12: Buildings & Admin | J12: 1202010202 | L12: Factory Building-18 | O12: 1 | P12: EA | Q12: X | S12: 40147 | T12: 43340 | Y12: 2018 | Z12: 2765865.1 | AA12: 01 | AB12: ZSLM | AC12: 7775 | AD12: 21 | AE12: 4 | AF12: =_xlfn.CONCAT(AG12," years ",AH12," days") -> 6 years 128 days | AG12: 6 | AH12: 128 | AI12: 2765865.1 | AJ12: 824246 | AK12: 2025 | AL12: 64388.19
A13: IN01 | B13: 1131100497 | E13: 0 | F13: Factory Building | G13: 9001 | H13: 9001000001 | I13: Buildings & Admin | J13: 1202010202 | L13: Factory Building-19 | O13: 1 | P13: EA | Q13: X | S13: 40446 | T13: 43340 | Y13: 2018 | Z13: 1886825.9 | AA13: 01 | AB13: ZSLM | AC13: 8067 | AD13: 22 | AE13: 1 | AF13: =_xlfn.CONCAT(AG13," years ",AH13," days") -> 6 years 128 days | AG13: 6 | AH13: 128 | AI13: 1886825.9 | AJ13: 541933 | AK13: 2025 | AL13: 42335.16
... A21: IN01 | B21: 1131400975 | E21: 0 | F21: Factory Building | G21: 9001 | H21: 9001000001 | I21: Buildings & Admin | J21: 1202010202 | L21: Factory Building-6 | O21: 1 | P21: EA | Q21: X | S21: 41364 | T21: 43340 | Y21: 2018 | Z21: 16675000 | AA21: 01 | AB21: ZSLM | AC21: 8979 | AD21: 24 | AE21: 7 | AF21: =_xlfn.CONCAT(AG21," years ",AH21," days") -> 6 years 128 days | AG21: 6 | AH21: 128 | AI21: 16675000 | AJ21: 4302926 | AK21: 2025 | AL21: 336137.37
A22: IN01 | B22: 1131401678 | E22: 0 | F22: Factory Building | G22: 9001 | H22: 9001000001 | I22: Buildings & Admin | J22: 1202010202 | L22: Toilet Line Orrisa Pan Fitting with Pipe Lin-7 | M22: e Complete | O22: 4 | P22: EA | Q22: X | S22: 42217 | T22: 43340 | Y22: 2018 | Z22: 55000 | AA22: 01 | AB22: ZSLM | AC22: 9819 | AD22: 26 | AE22: 11 | AF22: =_xlfn.CONCAT(AG22," years ",AH22," days") -> 6 years 128 days | AG22: 6 | AH22: 128 | AI22: 55000 | AJ22: 12978 | AK22: 2025 | AL22: 1014.2599
A23: IN01 | B23: 1131402939 | E23: 0 | F23: Factory Building | G23: 9001 | H23: 9001000002 | I23: Buildings & Admin | J23: 1202010202 | L23: BEING NON WALKABLE METAL CEILINGCAPITALISED -22 | M23: VIDE PURCHASE FROM ROYAL AIRCON BILL NO 286 DTD | O23: 1 | P23: EA | Q23: X | S23: 43577 | T23: 43577 | Y23: 2019 | Z23: 103395 | AA23: 01 | AB23: ZSLM | AC23: 10950 | AD23: 30 | AE23: 0 | AF23: =_xlfn.CONCAT(AG23," years ",AH23," days") -> 5 years 256 days | AG23: 5 | AH23: 256 | AI23: 103395 | AJ23: 19650 | AK23: 2025 | AL23: 1708.8575
A24: IN01 | B24: 1131403183 | E24: 0 | F24: Factory Building | G24: 9001 | H24: 9001000002 | I24: Buildings & Admin | J24: 1202010202 | L24: Being Non Walkable Metal Ceiling fitting wor-23 | M24: k done | O24: 1 | P24: EA | Q24: X | S24: 43817 | T24: 43817 | Y24: 2019 | Z24: 576753 | AA24: 01 | AB24: ZSLM | AC24: 10950 | AD24: 30 | AE24: 0 | AF24: =_xlfn.CONCAT(AG24," years ",AH24," days") -> 5 years 16 days | AG24: 5 | AH24: 16 | AI24: 576753 | AJ24: 96968 | AK24: 2025 | AL24: 9533.7868
A25: IN01 | B25: 1131403175 | E25: 0 | F25: Factory Building | G25: 9001 | H25: 9001000002 | I25: Buildings & Admin | J25: 1202010202 | L25: Being HR Sheets & HR Plates pur from Gayatri-24 | M25: Steel & Pipes vide inv no 0969 dt 27.11.19 ag P | O25: 1 | P25: EA | Q25: X | S25: 43801 | T25: 43801 | Y25: 2019 | Z25: 200669 | AA25: 01 | AB25: ZSLM | AC25: 10950 | AD25: 30 | AE25: 0 | AF25: =_xlfn.CONCAT(AG25," years ",AH25," days") -> 5 years 32 days | AG25: 5 | AH25: 32 | AI25: 200669 | AJ25: 33143 | AK25: 2025 | AL25: 3317.2282
A26: IN01 | B26: 1131403093 | E26: 0 | F26: Factory Building | G26: 9001 | H26: 9001000003 | I26: Buildings & Admin | J26: 1202010202 | L26: Being Construction work done by Jai Mata Con-25 | M26: struction vide inv no 09 dt 05.11.19 ag PO# SMPO | O26: 1 | P26: EA | Q26: X | S26: 43781 | T26: 43781 | Y26: 2019 | Z26: 733982 | AA26: 01 | AB26: ZSLM | AC26: 10950 | AD26: 30 | AE26: 0 | AF26: =_xlfn.CONCAT(AG26," years ",AH26," days") -> 5 years 52 days | AG26: 5 | AH26: 52 | AI26: 733982 | AJ26: 125816 | AK26: 2025 | AL26: 12132.398
A27: IN01 | B27: 1131403088 | E27: 0 | F27: Factory Building | G27: 9001 | H27: 9001000004 | I27: Buildings & Admin | J27: 1202010202 | L27: Being 3mm Epoxy Flooring work done by H A M -26 | M27: Corporation vide inv no 47 dt 09.11.19 ag PO# SM | O27: 1 | P27: EA | Q27: X | S27: 43771 | T27: 43771 | Y27: 2019 | Z27: 457331 | AA27: 01 | AB27: ZSLM | AC27: 10950 | AD27: 30 | AE27: 0 | AF27: =_xlfn.CONCAT(AG27," years ",AH27," days") -> 5 years 62 days | AG27: 5 | AH27: 62 | AI27: 457331 | AJ27: 78811 | AK27: 2025 | AL27: 7559.8226
A28: IN01 | B28: 1131403188 | E28: 0 | F28: Factory Building | G28: 9001 | H28: 9001000004 | I28: Buildings & Admin | J28: 1202010202 | L28: Being 3mm Epoxy Flooring work done by HAM Co-27 | M28: rporation vide inv no 57 dt 16.12.19 ag PO# SMPO | O28: 1 | P28: EA | Q28: X | S28: 43821 | T28: 43821 | Y28: 2019 | Z28: 111953 | AA28: 01 | AB28: ZSLM | AC28: 10950 | AD28: 30 | AE28: 0 | AF28: =_xlfn.CONCAT(AG28," years ",AH28," days") -> 5 years 12 days | AG28: 5 | AH28: 12 | AI28: 111953 | AJ28: 18782 | AK28: 2025 | AL28: 1850.0689
A29: IN01 | B29: 1131403286 | E29: 0 | F29: Factory Building | G29: 9001 | H29: 9001000005 | I29: Buildings & Admin | J29: 1202010202 | L29: Being New Compound wall work done by Pyramid-28 | M29: Construction vide inv no 3 dt 04.02.20 ag PO# S | O29: 1 | P29: EA | Q29: X | S29: 43931 | T29: 43931 | Y29: 2020 | Z29: 790821 | AA29: 01 | AB29: ZSLM | AC29: 10950 | AD29: 30 | AE29: 0 | AF29: =_xlfn.CONCAT(AG29," years ",AH29," days") -> 4 years 267 days | AG29: 4 | AH29: 267 | AI29: 790821 | AJ29: 124726 | AK29: 2025 | AL29: 13071.851
A30: IN01 | B30: 1131403288 | E30: 0 | F30: Factory Building | G30: 9001 | H30: 9001000006 | I30: Buildings & Admin | J30: 1202010202 | L30: Being MS Round & Square Bar pur from Sainath-29 | M30: Structures Pvt Ltd vide inv no GST3983 dt 08.01 | O30: 1 | P30: EA | Q30: X | S30: 43931 | T30: 43931 | Y30: 2020 | Z30: 32667 | AA30: 01 | AB30: ZSLM | AC30: 10950 | AD30: 30 | AE30: 0 | AF30: =_xlfn.CONCAT(AG30," years ",AH30," days") -> 4 years 267 days | AG30: 4 | AH30: 267 | AI30: 32667 | AJ30: 5152 | AK30: 2025 | AL30: 540.11288
A31: IN01 | B31: 1131403289 | E31: 0 | F31: Factory Building | G31: 9001 | H31: 9001000006 | I31: Buildings & Admin | J31: 1202010202 | L31: Being Main Gate Office Side Old Road RCC Ruf-30 | M31: f work done by Jai Mata Construction vide inv no | O31: 1 | P31: EA | Q31: X | S31: 43931 | T31: 43931 | Y31: 2020 | Z31: 216737 | AA31: 01 | AB31: ZSLM | AC31: 10950 | AD31: 30 | AE31: 0 | AF31: =_xlfn.CONCAT(AG31," years ",AH31," days") -> 4 years 267 days | AG31: 4 | AH31: 267 | AI31: 216737 | AJ31: 34183 | AK31: 2025 | AL31: 3582.68
A32: IN01 | B32: 1131403491 | E32: 0 | F32: Factory Building | G32: 9001 | H32: 9001000007 | I32: Buildings & Admin | J32: 1202010202 | L32: Being MS Chanel, Chakar Plate, MS angle, MS -31 | M32: Pipes pur from Sainath Structures Pvt Ltd vide i | O32: 1 | P32: EA | Q32: X | S32: 44183 | T32: 44183 | Y32: 2020 | Z32: 67468 | AA32: 01 | AB32: ZSLM | AC32: 10950 | AD32: 30 | AE32: 0 | AF32: =_xlfn.CONCAT(AG32," years ",AH32," days") -> 4 years 15 days | AG32: 4 | AH32: 15 | AI32: 67468 | AJ32: 9088 | AK32: 2025 | AL32: 1115.3797
A33: IN01 | B33: 1131403492 | E33: 0 | F33: Factory Building | G33: 9001 | H33: 9001000007 | I33: Buildings & Admin | J33: 1202010202 | L33: Being Fabrication Work for Extra Receiver In-32 | M33: stallation for Header Connecting With Support Wo | O33: 1 | P33: EA | Q33: X | S33: 44185 | T33: 44185 | Y33: 2020 | Z33: 19636 | AA33: 01 | AB33: ZSLM | AC33: 10950 | AD33: 30 | AE33: 0 | AF33: =_xlfn.CONCAT(AG33," years ",AH33," days") -> 4 years 13 days | AG33: 4 | AH33: 13 | AI33: 19636 | AJ33: 2641 | AK33: 2025 | AL33: 325.02228
... A49: IN01 | B49: 1131404646 | E49: 0 | F49: Factory Building | G49: 9001 | H49: 9001000016 | I49: Buildings & Admin | J49: 1202010202 | L49: Addition to New Building (Addition to New Pl-48 | M49: ant) | O49: 1 | P49: EA | Q49: X | S49: 44986 | T49: 44986 | Y49: 2023 | Z49: 1.5146637e+08 | AA49: 01 | AB49: ZSLM | AC49: 10950 | AD49: 30 | AE49: 0 | AF49: =_xlfn.CONCAT(AG49," years ",AH49," days") -> 1 years 307 days | AG49: 1 | AH49: 307 | AI49: 1.5146637e+08 | AJ49: 9295470 | AK49: 2025 | AL49: 2503690.7
A50: IN01 | B50: 1131404732 | E50: 0 | F50: Factory Building | G50: 9001 | H50: 9001000017 | I50: Buildings & Admin | J50: 1202010202 | L50: Improvement In Factory Building-49 | O50: 1 | P50: EA | Q50: X | S50: 45047 | T50: 45047 | Y50: 2023 | Z50: 3552291.3 | AA50: 01 | AB50: ZSLM | AC50: 10950 | AD50: 30 | AE50: 0 | AF50: =_xlfn.CONCAT(AG50," years ",AH50," days") -> 1 years 246 days | AG50: 1 | AH50: 246 | AI50: 3552291.3 | AJ50: 198215 | AK50: 2025 | AL50: 58717.85
A51: IN01 | B51: 1131404801 | E51: 0 | F51: Factory Building | G51: 9001 | H51: 9001000017 | I51: Buildings & Admin | J51: 1202010202 | L51: B/NO. 033 DT: 15.06.23 OF GRACE ENGINEERING -50 | M51: WORKS BOOKED FOR STP PLANT ROOF MAKING , JALLY | O51: 1 | P51: EA | Q51: X | S51: 45108 | T51: 45108 | Y51: 2023 | Z51: 47780 | AA51: 01 | AB51: ZSLM | AC51: 10950 | AD51: 30 | AE51: 0 | AF51: =_xlfn.CONCAT(AG51," years ",AH51," days") -> 1 years 185 days | AG51: 1 | AH51: 185 | AI51: 47780 | AJ51: 2400 | AK51: 2025 | AL51: 789.6968
A52: IN01 | B52: 1131404809 | E52: 0 | F52: Factory Building | G52: 9001 | H52: 9001000017 | I52: Buildings & Admin | J52: 1202010202 | L52: B/NO. 43 DT: 03.07.23 OF PRAFULLA SHEET BOOK-51 | M52: ED FOR PVC PIPE RAIN WATER LINE FITTING , ELBOW | O52: 1 | P52: EA | Q52: X | S52: 45111 | T52: 45111 | Y52: 2023 | Z52: 34522 | AA52: 01 | AB52: ZSLM | AC52: 10950 | AD52: 30 | AE52: 0 | AF52: =_xlfn.CONCAT(AG52," years ",AH52," days") -> 1 years 182 days | AG52: 1 | AH52: 182 | AI52: 34522 | AJ52: 1725 | AK52: 2025 | AL52: 570.16128
A53: IN01 | B53: 1131404920 | E53: 0 | F53: Factory Building | G53: 9001 | H53: 9001000018 | I53: Buildings & Admin | J53: 1202010202 | L53: Being Factory Building work Capitalised-52 | O53: 1 | P53: EA | Q53: X | S53: 45199 | T53: 45199 | Y53: 2023 | Z53: 9299379.8 | AA53: 01 | AB53: ZSLM | AC53: 10950 | AD53: 30 | AE53: 0 | AF53: =_xlfn.CONCAT(AG53," years ",AH53," days") -> 1 years 94 days | AG53: 1 | AH53: 94 | AI53: 9299379.8 | AJ53: 389810 | AK53: 2025 | AL53: 153715.39
A54: IN01 | B54: 1131404966 | E54: 0 | F54: Factory Building | G54: 9001 | H54: 9001000019 | I54: Buildings & Admin | J54: 1202010202 | L54: B/NO. 27 DT: 23.05.23 OF PANCHAL INDUSTRIES -53 | M54: BOOKED FOR PUR ROLLING SHUTTER VIDE TSGO/23-24/ | O54: 10 | P54: EA | Q54: X | S54: 45231 | T54: 45231 | Y54: 2023 | Z54: 474388 | AA54: 01 | AB54: ZSLM | AC54: 10950 | AD54: 30 | AE54: 0 | AF54: =_xlfn.CONCAT(AG54," years ",AH54," days") -> 1 years 62 days | AG54: 1 | AH54: 62 | AI54: 474388 | AJ54: 18499 | AK54: 2025 | AL54: 7841.4479
A55: IN01 | B55: 1131404967 | E55: 0 | F55: Factory Building | G55: 9001 | H55: 9001000019 | I55: Buildings & Admin | J55: 1202010202 | L55: B/NO. 88 DT: 04.08.23 OF PANCHAL INDUSTRIES -54 | M55: BOOKED FOR PUR GLASS DOOR , RADAR & DIGITAL LOC | O55: 47 | P55: EA | Q55: X | S55: 45231 | T55: 45231 | Y55: 2023 | Z55: 153400 | AA55: 01 | AB55: ZSLM | AC55: 10950 | AD55: 30 | AE55: 0 | AF55: =_xlfn.CONCAT(AG55," years ",AH55," days") -> 1 years 62 days | AG55: 1 | AH55: 62 | AI55: 153400 | AJ55: 5982 | AK55: 2025 | AL55: 2535.5525
A56: IN01 | B56: 1131404968 | E56: 0 | F56: Factory Building | G56: 9001 | H56: 9001000019 | I56: Buildings & Admin | J56: 1202010202 | L56: B/NO. 04 DT: 09.09.23 OF JAI MATA CONSTRUCTI-55 | M56: ON BOOKED FOR HT YARD 2500 KVA AREA WALL BREAKIN | O56: 1 | P56: EA | Q56: X | S56: 45231 | T56: 45231 | Y56: 2023 | Z56: 54042 | AA56: 01 | AB56: ZSLM | AC56: 10950 | AD56: 30 | AE56: 0 | AF56: =_xlfn.CONCAT(AG56," years ",AH56," days") -> 1 years 62 days | AG56: 1 | AH56: 62 | AI56: 54042 | AJ56: 2107 | AK56: 2025 | AL56: 893.68822
A57: IN01 | B57: 1131404969 | E57: 0 | F57: Factory Building | G57: 9001 | H57: 9001000019 | I57: Buildings & Admin | J57: 1202010202 | L57: B/NO. 05 DT: 11.09.23 OF JAI MATA CONSTRUCTI-56 | M57: ON BOOKED FOR ROAD EXCAVATION , RCC 200 MM THIK | O57: 1 | P57: EA | Q57: X | S57: 45231 | T57: 45231 | Y57: 2023 | Z57: 3211253 | AA57: 01 | AB57: ZSLM | AC57: 10950 | AD57: 30 | AE57: 0 | AF57: =_xlfn.CONCAT(AG57," years ",AH57," days") -> 1 years 62 days | AG57: 1 | AH57: 62 | AI57: 3211253 | AJ57: 125224 | AK57: 2025 | AL57: 53081.189
A58: IN01 | B58: 1131404970 | E58: 0 | F58: Factory Building | G58: 9001 | H58: 9001000019 | I58: Buildings & Admin | J58: 1202010202 | L58: B/NO. BILL/23-24/19 DT: 01.10.23 OF PK ENTER-57 | M58: PRISES BOOEKD FOR CIVIL WORK AGST PO SMPOCG/23-2 | O58: 1 | P58: EA | Q58: X | S58: 45231 | T58: 45231 | Y58: 2023 | Z58: 111523 | AA58: 01 | AB58: ZSLM | AC58: 10950 | AD58: 30 | AE58: 0 | AF58: =_xlfn.CONCAT(AG58," years ",AH58," days") -> 1 years 62 days | AG58: 1 | AH58: 62 | AI58: 111523 | AJ58: 4349 | AK58: 2025 | AL58: 1843.3273
A59: IN01 | B59: 1131404971 | E59: 0 | F59: Factory Building | G59: 9001 | H59: 9001000019 | I59: Buildings & Admin | J59: 1202010202 | L59: B/NO. 08 DT: 05.10.23 OF JAI MATA CONSTRUCTI-58 | M59: ON BOOKED FOR ROAD EXCAVATION , GSB FILLING , ST | O59: 1 | P59: EA | Q59: X | S59: 45231 | T59: 45231 | Y59: 2023 | Z59: 625968 | AA59: 01 | AB59: ZSLM | AC59: 10950 | AD59: 30 | AE59: 0 | AF59: =_xlfn.CONCAT(AG59," years ",AH59," days") -> 1 years 62 days | AG59: 1 | AH59: 62 | AI59: 625968 | AJ59: 24410 | AK59: 2025 | AL59: 10346.945
A60: IN01 | B60: 1131404972 | E60: 0 | F60: Factory Building | G60: 9001 | H60: 9001000019 | I60: Buildings & Admin | J60: 1202010202 | L60: B/NO. 354/23-24 DT: 06.10.23 OF LAXMI ELE BO-59 | M60: OKED FOR PU FLOORING AGST PO SMPOCG/23-24/202 DT | O60: 46 | P60: EA | Q60: X | S60: 45231 | T60: 45231 | Y60: 2023 | Z60: 80334 | AA60: 01 | AB60: ZSLM | AC60: 10950 | AD60: 30 | AE60: 0 | AF60: =_xlfn.CONCAT(AG60," years ",AH60," days") -> 1 years 62 days | AG60: 1 | AH60: 62 | AI60: 80334 | AJ60: 3133 | AK60: 2025 | AL60: 1327.5545
A61: IN01 | B61: 1131404973 | E61: 0 | F61: Factory Building | G61: 9001 | H61: 9001000019 | I61: Buildings & Admin | J61: 1202010202 | L61: B/NO. 053 DT: 16.10.23 OF GRACE ENGINEERING-60 | M61: BOOKED FOR HAND RAILING MAKING OF UTILITY AGTS | O61: 1 | P61: EA | Q61: X | S61: 45231 | T61: 45231 | Y61: 2023 | Z61: 99120 | AA61: 01 | AB61: ZSLM | AC61: 10950 | AD61: 30 | AE61: 0 | AF61: =_xlfn.CONCAT(AG61," years ",AH61," days") -> 1 years 62 days | AG61: 1 | AH61: 62 | AI61: 99120 | AJ61: 3865 | AK61: 2025 | AL61: 1638.6493
A62: IN01 | B62: 1131405014 | E62: 0 | F62: Factory Building | G62: 9001 | H62: 9001000020 | I62: Buildings & Admin | J62: 1202010202 | L62: BEING T/F THROUGH J/V AGST B/NO. S-123/2023--61 | M62: 24 DT: 10.10.23 OF PRAGMATIC HVAC BOOKED FOR PUR | O62: 67 | P62: EA | Q62: X | S62: 45261 | T62: 45261 | Y62: 2023 | Z62: 100327 | AA62: 01 | AB62: ZSLM | AC62: 10950 | AD62: 30 | AE62: 0 | AF62: =_xlfn.CONCAT(AG62," years ",AH62," days") -> 1 years 32 days | AG62: 1 | AH62: 32 | AI62: 100327 | AJ62: 3637 | AK62: 2025 | AL62: 1658.7996
A63: IN01 | B63: 1131405015 | E63: 0 | F63: Factory Building | G63: 9001 | H63: 9001000020 | I63: Buildings & Admin | J63: 1202010202 | L63: BEING AMT T/F THROUGH J/V AGST B/NO. 1099 DT-62 | M63: : 06.11.23 OF SOLANKI ENTERPRISES BOOKED FOR PUR | O63: 2 | P63: EA | Q63: X | S63: 45261 | T63: 45261 | Y63: 2023 | Z63: 14160 | AA63: 01 | AB63: ZSLM | AC63: 10950 | AD63: 30 | AE63: 0 | AF63: =_xlfn.CONCAT(AG63," years ",AH63," days") -> 1 years 32 days | AG63: 1 | AH63: 32 | AI63: 14160 | AJ63: 513 | AK63: 2025 | AL63: 234.4411
A64: IN01 | B64: 1131405075 | E64: 0 | F64: Factory Building | G64: 9001 | H64: 9001000021 | I64: Buildings & Admin | J64: 1202010202 | L64: BEING T/F THROUGH J/V AGTS B/NO. 075 DT: 22.-63 | M64: 01.24 OF GRACE ENGINEERING WORKS BOOKED FOR RAMP | O64: 1 | P64: EA | Q64: X | S64: 45314 | T64: 45314 | Y64: 2024 | Z64: 30007 | AA64: 01 | AB64: ZSLM | AC64: 10950 | AD64: 30 | AE64: 0 | AF64: =_xlfn.CONCAT(AG64," years ",AH64," days") -> 0 years 344 days | AG64: 0 | AH64: 344 | AI64: 30007 | AJ64: 943 | AK64: 2025 | AL64: 495.69178
A65: IN01 | B65: 1131405107 | E65: 0 | F65: Factory Building | G65: 9001 | H65: 9001000022 | I65: Buildings & Admin | J65: 1202010202 | L65: BEING T/F THROUGH J/V AGST B/NO. BILL/23-24/-64 | M65: 30 DTD: 02.02.24 OF PK ENTERPRISES BOOKED FOR RC | O65: 1 | P65: EA | Q65: X | S65: 45345 | T65: 45345 | Y65: 2024 | Z65: 316483 | AA65: 01 | AB65: ZSLM | AC65: 10950 | AD65: 30 | AE65: 0 | AF65: =_xlfn.CONCAT(AG65," years ",AH65," days") -> 0 years 313 days | AG65: 0 | AH65: 313 | AI65: 316483 | AJ65: 9047 | AK65: 2025 | AL65: 5230.8632
... A67: IN01 | B67: 1131405109 | E67: 0 | F67: Factory Building | G67: 9001 | H67: 9001000022 | I67: Buildings & Admin | J67: 1202010202 | L67: BEING T/F THROUGH J/V AGST B/NO. BILL/23-24/-66 | M67: 31 DTD: 02.02.24 OF P K ENTERPRISES BOOEKD FOR C | O67: 1 | P67: EA | Q67: X | S67: 45346 | T67: 45346 | Y67: 2024 | Z67: 1245065 | AA67: 01 | AB67: ZSLM | AC67: 10950 | AD67: 30 | AE67: 0 | AF67: =_xlfn.CONCAT(AG67," years ",AH67," days") -> 0 years 312 days | AG67: 0 | AH67: 312 | AI67: 1245065 | AJ67: 35476 | AK67: 2025 | AL67: 20580.351
A68: IN01 | B68: 1131405213 | E68: 0 | F68: Factory Building | G68: 9001 | H68: 9001000023 | I68: Buildings & Admin | J68: 1202010202 | L68: Fire hydrant Foam Monitor-67 | O68: 1 | P68: EA | Q68: X | S68: 45444 | T68: 45444 | Y68: 2024 | Z68: 102042 | AA68: 01 | AB68: ZSLM | AC68: 1825 | AD68: 5 | AE68: 0 | AF68: =_xlfn.CONCAT(AG68," years ",AH68," days") -> 0 years 214 days | AG68: 0 | AH68: 214 | AI68: 102042 | AJ68: 11965 | AK68: 2025 | AL68: 10120.803
A69: IN01 | B69: 1131405214 | E69: 0 | F69: Factory Building | G69: 9001 | H69: 9001000023 | I69: Buildings & Admin | J69: 1202010202 | L69: Being installation in new Security cabin & E-68 | M69: mergency control for Fire safety | O69: 1 | P69: EA | Q69: X | S69: 45453 | T69: 45453 | Y69: 2024 | Z69: 51201 | AA69: 01 | AB69: ZSLM | AC69: 1825 | AD69: 5 | AE69: 0 | AF69: =_xlfn.CONCAT(AG69," years ",AH69," days") -> 0 years 205 days | AG69: 0 | AH69: 205 | AI69: 51201 | AJ69: 5751 | AK69: 2025 | AL69: 5078.3622
A70: IN01 | B70: 1131405260 | E70: 0 | F70: Factory Building | G70: 9001 | H70: 9001000024 | I70: Buildings & Admin | J70: 1202010202 | L70: Being Workers canteen ( New) Capitalised-69 | O70: 1 | P70: EA | Q70: X | S70: 45530 | T70: 45530 | Y70: 2024 | Z70: 838800 | AA70: 01 | AB70: ZSLM | AC70: 10950 | AD70: 30 | AE70: 0 | AF70: =_xlfn.CONCAT(AG70," years ",AH70," days") -> 0 years 128 days | AG70: 0 | AH70: 128 | AI70: 838800 | AJ70: 9805 | AK70: 2025 | AL70: 13865.247
A71: IN01 | B71: 1131405261 | E71: 0 | F71: Factory Building | G71: 9001 | H71: 9001000025 | I71: Buildings & Admin | J71: 1202010202 | L71: BEING T/F THROUGH J/V AGST B/NO. BILL/25-26/-70 | M71: 05 DTD: 01.06.25 OF P K ENTERPRISES BOOEKD FOR | O71: 1 | P71: EA | Q71: X | S71: 45812 | T71: 45812 | Y71: 2025 | Z71: 0 | AA71: 01 | AB71: ZSLM | AC71: 10950 | AD71: 30 | AE71: 0 | AF71: =_xlfn.CONCAT(AG71," years ",AH71," days") -> 0 years 0 days | AG71: 0 | AH71: 0 | AI71: 222190 | AJ71: 0 | AK71: 2025 | AL71: 547.86575
A72: IN01 | B72: 1131105131 | E72: 0 | F72: Factory Building | G72: 9001 | H72: 9001000026 | I72: Buildings & Admin | J72: 1202010202 | L72: Factory Building work Capitalised-71 | O72: 1 | P72: EA | Q72: X | S72: 45382 | T72: 45382 | Y72: 2024 | Z72: 5399840.7 | AA72: 01 | AB72: ZSLM | AC72: 10950 | AD72: 30 | AE72: 0 | AF72: =_xlfn.CONCAT(AG72," years ",AH72," days") -> 0 years 276 days | AG72: 0 | AH72: 276 | AI72: 5399840.7 | AJ72: 136599 | AK72: 2025 | AL72: 89257.35
A73: IN01 | B73: 1131400003 | E73: 0 | F73: Flat | G73: 9002 | H73: 9002000001 | I73: Buildings & Admin | J73: 1202010202 | L73: Flat (A-306 - Horizon)-72 | O73: 1 | P73: EA | Q73: X | S73: 36445 | T73: 43340 | Y73: 2018 | Z73: 1400000 | AA73: 01 | AB73: ZSLM | AC73: 11352 | AD73: 31 | AE73: 1 | AF73: =_xlfn.CONCAT(AG73," years ",AH73," days") -> 6 years 128 days | AG73: 6 | AH73: 128 | AI73: 1400000 | AJ73: 285747 | AK73: 2025 | AL73: 22322.063
A74: IN01 | B74: 1131400006 | E74: 0 | F74: Flat | G74: 9002 | H74: 9002000002 | I74: Buildings & Admin | J74: 1202010202 | L74: Flat (One) (L-4 - Parth CHS)-73 | O74: 1 | P74: EA | Q74: X | S74: 36707 | T74: 43340 | Y74: 2018 | Z74: 800000 | AA74: 01 | AB74: ZSLM | AC74: 11607 | AD74: 31 | AE74: 10 | AF74: =_xlfn.CONCAT(AG74," years ",AH74," days") -> 6 years 128 days | AG74: 6 | AH74: 128 | AI74: 800000 | AJ74: 159697 | AK74: 2025 | AL74: 12474.965
A75: IN01 | B75: 1131400007 | E75: 0 | F75: Flat | G75: 9002 | H75: 9002000003 | I75: Buildings & Admin | J75: 1202010202 | L75: Flat (Three) (L-22, 23, 26 - Parth CHS) -74 | O75: 1 | P75: EA | Q75: X | S75: 36891 | T75: 43340 | Y75: 2018 | Z75: 2700000 | AA75: 01 | AB75: ZSLM | AC75: 11790 | AD75: 32 | AE75: 4 | AF75: =_xlfn.CONCAT(AG75," years ",AH75," days") -> 6 years 128 days | AG75: 6 | AH75: 128 | AI75: 2700000 | AJ75: 530611 | AK75: 2025 | AL75: 41450.069
A76: IN01 | B76: 1131400164 | E76: 0 | F76: Flat | G76: 9002 | H76: 9002000004 | I76: Buildings & Admin | J76: 1202010202 | L76: 2 Nos. Flat no 17 & 16 Area 16.84 Sq Miters -75 | M76: Purchase | O76: 2 | P76: EA | Q76: X | S76: 38960 | T76: 43340 | Y76: 2018 | Z76: 2900000 | AA76: 01 | AB76: ZSLM | AC76: 13870 | AD76: 38 | AE76: 0 | AF76: =_xlfn.CONCAT(AG76," years ",AH76," days") -> 6 years 128 days | AG76: 6 | AH76: 128 | AI76: 2900000 | AJ76: 484448 | AK76: 2025 | AL76: 37844.718
A77: IN01 | B77: 1131102149 | E77: 0 | F77: Flat | G77: 9002 | H77: 9002000005 | I77: Buildings & Admin | J77: 1202010202 | K77: TPAC/SIL/WAD-005 | L77: Astha Hights-76 | O77: 1 | P77: EA | Q77: X | S77: 42649 | T77: 43340 | Y77: 2018 | Z77: 1 | AA77: 01 | AB77: ZSLM | AC77: 18078 | AD77: 49 | AE77: 6 | AF77: =_xlfn.CONCAT(AG77," years ",AH77," days") -> 6 years 128 days | AG77: 6 | AH77: 128 | AI77: 1 | AJ77: 1 | AK77: 2025 | AL77: 0
A78: IN01 | B78: 1191402530 | E78: 0 | F78: Freehold Land | G78: 9005 | H78: 9005000001 | I78: Buildings & Admin | J78: 1202010202 | L78: Land-77 | O78: 1 | P78: EA | Q78: X | S78: 0 | T78: 43340 | Y78: 2018 | Z78: 47000000 | AA78: 01 | AB78: ZSLM | AC78: 0 | AD78: 0 | AE78: 0 | AF78: =_xlfn.CONCAT(AG78," years ",AH78," days") -> 0 years 0 days | AG78: 0 | AH78: 0 | AI78: 47000000 | AJ78: 0 | AK78: 2025 | AL78: 0
A79: IN01 | B79: 1191403090 | E79: 0 | F79: Freehold Land | G79: 9005 | H79: 9005000002 | I79: Buildings & Admin | J79: 1202010202 | L79: Freehold Land Survey No-215/2/2-78 | O79: 1 | P79: EA | Q79: X | S79: 43775 | T79: 43775 | Y79: 2019 | Z79: 86390500 | AA79: 01 | AB79: ZSLM | AC79: 0 | AD79: 0 | AE79: 0 | AF79: =_xlfn.CONCAT(AG79," years ",AH79," days") -> 0 years 0 days | AG79: 0 | AH79: 0 | AI79: 86390500 | AJ79: 0 | AK79: 2025 | AL79: 0
A80: IN01 | B80: 1101400906 | E80: 0 | F80: Factory Equipment & Tools | G80: 9007 | H80: 9007000001 | I80: Utility | J80: 1202010217 | K80: TPAC/SIL/RO-001 | L80: Ro Plant 5000Lph Bill No. 287/21.1.13 Scale -79 | M80: Guard | O80: 1 | P80: EA | Q80: X | S80: 41297 | T80: 43340 | Y80: 2018 | Z80: 410000 | AA80: 01 | AB80: ZSLM | AC80: 3431 | AD80: 9 | AE80: 5 | AF80: =_xlfn.CONCAT(AG80," years ",AH80," days") -> 6 years 128 days | AG80: 6 | AH80: 128 | AI80: 410000 | AJ80: 276878 | AK80: 2025 | AL80: 21629.724
A81: IN01 | B81: 1101404676 | E81: 0 | F81: Factory Equipment & Tools | G81: 9007 | H81: 9007000002 | I81: Utility | J81: 1202010217 | K81: TPAC/SIL/RO-002 | L81: T/F THROUGH J/V AGST B/NO. GST/SG054/22-23 D-81 | M81: T: 26.04.22 BOOKED FOR PUR RO PLANT 500 LPH VIDE | O81: 1 | P81: EA | Q81: X | S81: 45000 | T81: 45000 | Y81: 2023 | Z81: 2169334.2 | AA81: 01 | AB81: ZSLM | AC81: 3650 | AD81: 10 | AE81: 0 | AF81: =_xlfn.CONCAT(AG81," years ",AH81," days") -> 1 years 293 days | AG81: 1 | AH81: 293 | AI81: 2169334.2 | AJ81: 391074 | AK81: 2025 | AL81: 107575.7
A82: IN01 | B82: 1101101761 | D82: 1101404676 | E82: 1 | F82: Factory Equipment & Tools | G82: 9007 | H82: 9007000002 | I82: Utility | J82: 1202010217 | L82: Water Purification Ro System 250ltr/hr-82 | O82: 1 | P82: EA | Q82: X | S82: 42307 | T82: 43340 | Y82: 2018 | Z82: 155000 | AA82: 01 | AB82: ZSLM | AC82: 4417 | AD82: 12 | AE82: 1 | AF82: =_xlfn.CONCAT(AG82," years ",AH82," days") -> 6 years 128 days | AG82: 6 | AH82: 128 | AI82: 155000 | AJ82: 81307 | AK82: 2025 | AL82: 6352.0446
A83: IN01 | B83: 1101400341 | E83: 0 | F83: Factory Equipment & Tools | G83: 9007 | H83: 9007000003 | I83: Utility | J83: 1202010217 | K83: CHILLER140TR | L83: Trans Chiller with all accessories-84 | O83: 1 | P83: EA | Q83: X | S83: 39966 | T83: 43340 | Y83: 2018 | Z83: 3150000 | AA83: 01 | AB83: ZSLM | AC83: 2117 | AD83: 5 | AE83: 10 | AF83: =_xlfn.CONCAT(AG83," years ",AH83," days") -> 5 years 292 days | AG83: 5 | AH83: 292 | AI83: 3150000 | AJ83: 3150000 | AK83: 2025 | AL83: 0
A84: IN01 | B84: 1101404647 | D84: 1101400341 | E84: 1 | F84: Factory Equipment & Tools | G84: 9007 | H84: 9007000003 | I84: Utility | J84: 1202010217 | L84: Being Expences towords SS 304 pipe 4 Schedul-85 | M84: e 20 Qty.42nos,Short Elbow 4 schedule 20 Qty.12n | O84: 1 | P84: EA | Q84: X | S84: 44986 | T84: 44986 | Y84: 2023 | Z84: 82374 | AA84: 01 | AB84: ZSLM | AC84: 3650 | AD84: 10 | AE84: 0 | AF84: =_xlfn.CONCAT(AG84," years ",AH84," days") -> 1 years 307 days | AG84: 1 | AH84: 307 | AI84: 82374 | AJ84: 15166 | AK84: 2025 | AL84: 4084.691
A85: IN01 | B85: 1101404922 | D85: 1101400341 | E85: 2 | F85: Factory Equipment & Tools | G85: 9007 | H85: 9007000003 | I85: Utility | J85: 1202010217 | L85: B/NO. 047 DT: 19.09.23 OF GRACE ENGINEERING -86 | M85: WORKS BOOKED FOR DRYER STAND MAKING FOR 70 DPH M | O85: 1 | P85: EA | Q85: X | S85: 45199 | T85: 45199 | Y85: 2023 | Z85: 24875 | AA85: 01 | AB85: ZSLM | AC85: 3650 | AD85: 10 | AE85: 0 | AF85: =_xlfn.CONCAT(AG85," years ",AH85," days") -> 1 years 94 days | AG85: 1 | AH85: 94 | AI85: 24875 | AJ85: 3128 | AK85: 2025 | AL85: 1233.6438
A86: IN01 | B86: 1101404936 | D86: 1101400341 | E86: 3 | F86: Factory Equipment & Tools | G86: 9007 | H86: 9007000003 | I86: Utility | J86: 1202010217 | L86: Being purchased MS PIPE VIDE TSGO/23-24/387 -87 | M86: DT: 25.09.23 from Solanki Enterprises and PUR CO | O86: 1 | P86: EA | Q86: X | S86: 45199 | T86: 45199 | Y86: 2023 | Z86: 6695 | AA86: 01 | AB86: ZSLM | AC86: 3650 | AD86: 10 | AE86: 0 | AF86: =_xlfn.CONCAT(AG86," years ",AH86," days") -> 1 years 94 days | AG86: 1 | AH86: 94 | AI86: 6695 | AJ86: 842 | AK86: 2025 | AL86: 331.91781
A87: IN01 | B87: 1101104016 | D87: 1101400341 | E87: 4 | F87: Factory Equipment & Tools | G87: 9007 | H87: 9007000003 | I87: Utility | J87: 1202010217 | K87: Chiller 140 TR ( Assesories) | L87: B/NO: 472 DT: 27.1.2022 BEING PURCHASED AS A-88 | M87: LUMINIUM ARMOURED CABLE & COPPER FLEXIBLE CABLE | O87: 202 | P87: EA | Q87: X | S87: 44620 | T87: 44620 | Y87: 2022 | Z87: 503961 | AA87: 01 | AB87: ZSLM | AC87: 3650 | AD87: 10 | AE87: 0 | AF87: =_xlfn.CONCAT(AG87," years ",AH87," days") -> 2 years 308 days | AG87: 2 | AH87: 308 | AI87: 503961 | AJ87: 143318 | AK87: 2025 | AL87: 24991.167
A88: IN01 | B88: 1101400661 | E88: 0 | F88: Factory Equipment & Tools | G88: 9007 | H88: 9007000004 | I88: Utility | J88: 1202010217 | K88: CHILLER170TR + ATB | L88: import 170 TR WATER COOLED SCREW CHILLER ,MO-90 | M88: DEL NO,CRTHD QTY-1, TOTAL COST US $ 43000/-CIF R | O88: 1 | P88: EA | Q88: X | S88: 40817 | T88: 43340 | Y88: 2018 | Z88: 1300000 | AA88: 01 | AB88: ZSLM | AC88: 2957 | AD88: 8 | AE88: 1 | AF88: =_xlfn.CONCAT(AG88," years ",AH88," days") -> 6 years 128 days | AG88: 6 | AH88: 128 | AI88: 1300000 | AJ88: 1018634 | AK88: 2025 | AL88: 79573.643
A89: IN01 | B89: 1101405290 | D89: 1101400661 | E89: 1 | F89: Factory Equipment & Tools | G89: 9007 | H89: 9007000004 | I89: Utility | J89: 1202010217 | K89: Chiller 170 TR ( Assesories) | L89: new chilling water pipe line capitalised-91 | O89: 1 | P89: EA | Q89: X | S89: 45524 | T89: 45524 | Y89: 2024 | Z89: 266656.5 | AA89: 01 | AB89: ZSLM | AC89: 3650 | AD89: 10 | AE89: 0 | AF89: =_xlfn.CONCAT(AG89," years ",AH89," days") -> 0 years 134 days | AG89: 0 | AH89: 134 | AI89: 266656.5 | AJ89: 9790 | AK89: 2025 | AL89: 13222.821
A90: IN01 | B90: 1101404540 | E90: 0 | F90: Factory Equipment & Tools | G90: 9007 | H90: 9007000005 | I90: Utility | J90: 1202010217 | K90: CHILLER500TR + ATB (Accessories) | L90: 500TR CENTRIFUGAL CHILLER & ITS ACESSARY.(Ad-93 | M90: dition to New Plant) | O90: 1 | P90: EA | Q90: X | S90: 44910 | T90: 44910 | Y90: 2022 | Z90: 4602270 | AA90: 01 | AB90: ZSLM | AC90: 3650 | AD90: 10 | AE90: 0 | AF90: =_xlfn.CONCAT(AG90," years ",AH90," days") -> 2 years 18 days | AG90: 2 | AH90: 18 | AI90: 4602270 | AJ90: 943150 | AK90: 2025 | AL90: 228222.29
A91: IN01 | B91: 1101404673 | D91: 1101404540 | E91: 1 | F91: Factory Equipment & Tools | G91: 9007 | H91: 9007000005 | I91: Utility | J91: 1202010217 | K91: CHILLER500TR + ATB | L91: T/F THROUGH J/V AGST B/NO 8260588 DT: 13.04.-94 | M91: 22 OF BOOKED FOR PUR WATER COOLED CENTRIFUGAL C | O91: 1 | P91: EA | Q91: X | S91: 45000 | T91: 45000 | Y91: 2023 | Z91: 12178087 | AA91: 01 | AB91: ZSLM | AC91: 3650 | AD91: 10 | AE91: 0 | AF91: =_xlfn.CONCAT(AG91," years ",AH91," days") -> 1 years 293 days | AG91: 1 | AH91: 293 | AI91: 12178087 | AJ91: 2195392 | AK91: 2025 | AL91: 603899.73
A92: IN01 | B92: 1101405093 | D92: 1101404540 | E92: 2 | F92: Factory Equipment & Tools | G92: 9007 | H92: 9007000005 | I92: Utility | J92: 1202010217 | L92: BEING T/F THROUGH J/V AGST B/NO. ACPL/131/23-95 | M92: -24 DT: 02.02.24 OF AMICRON CLEANTECH BOOKED FOR | O92: 1080 | P92: EA | Q92: X | S92: 45327 | T92: 45327 | Y92: 2024 | Z92: 206800 | AA92: 01 | AB92: ZSLM | AC92: 3650 | AD92: 10 | AE92: 0 | AF92: =_xlfn.CONCAT(AG92," years ",AH92," days") -> 0 years 331 days | AG92: 0 | AH92: 331 | AI92: 206800 | AJ92: 18754 | AK92: 2025 | AL92: 10254.658
A93: IN01 | B93: 1101104040 | D93: 1101404540 | E93: 3 | F93: Factory Equipment & Tools | G93: 9007 | H93: 9007000005 | I93: Utility | J93: 1202010217 | L93: Being Booked for charges towards Comissionin-96 | M93: g for 1 no Trane chiller from Trane Technologies | O93: 1 | P93: EA | Q93: X | S93: 44622 | T93: 44622 | Y93: 2022 | Z93: 87000 | AA93: 01 | AB93: ZSLM | AC93: 3650 | AD93: 10 | AE93: 0 | AF93: =_xlfn.CONCAT(AG93," years ",AH93," days") -> 2 years 306 days | AG93: 2 | AH93: 306 | AI93: 87000 | AJ93: 24694 | AK93: 2025 | AL93: 4313.9452
A94: IN01 | B94: 1101400916 | E94: 0 | F94: Factory Equipment & Tools | G94: 9007 | H94: 9007000006 | I94: Utility | J94: 1202010217 | K94: PHE -05 (ALFA LAVEL) PHE -06 (ALFA LAVEL) | L94: Plate Heat Exchanger Tl 10 Pfm With 152 Plat-98 | M94: es-2 Pcs.Agst.Bno:8 Dt:21.01.13 From Pastan Engi | O94: 1 | P94: EA | Q94: X | S94: 41303 | T94: 43340 | Y94: 2018 | Z94: 630000 | AA94: 01 | AB94: ZSLM | AC94: 3431 | AD94: 9 | AE94: 5 | AF94: =_xlfn.CONCAT(AG94," years ",AH94," days") -> 6 years 128 days | AG94: 6 | AH94: 128 | AI94: 630000 | AJ94: 425447 | AK94: 2025 | AL94: 33235.6
A95: IN01 | B95: 1101401778 | E95: 0 | F95: Factory Equipment & Tools | G95: 9007 | H95: 9007000007 | I95: Utility | J95: 1202010217 | K95: PHE -04 (ALFA LAVEL) | L95: Plate Heat Exchanger TL 10PFM with 155 Plate-100 | M95: s | O95: 1 | P95: EA | Q95: X | S95: 42323 | T95: 43340 | Y95: 2018 | Z95: 410000 | AA95: 01 | AB95: ZSLM | AC95: 4417 | AD95: 12 | AE95: 1 | AF95: =_xlfn.CONCAT(AG95," years ",AH95," days") -> 6 years 128 days | AG95: 6 | AH95: 128 | AI95: 410000 | AJ95: 215071 | AK95: 2025 | AL95: 16801.312
A96: IN01 | B96: 1101400923 | E96: 0 | F96: Factory Equipment & Tools | G96: 9007 | H96: 9007000008 | I96: Utility | J96: 1202010217 | L96: Grundfos Make Pump Crcm 64-2 & Nb 125-250/24-102 | M96: 8 Cooling Tower Agst.Bno:260 Dt:30.01.2013 From | O96: 1 | P96: EA | Q96: X | S96: 41307 | T96: 43340 | Y96: 2018 | Z96: 200000 | AA96: 01 | AB96: ZSLM | AC96: 1606 | AD96: 4 | AE96: 5 | AF96: =_xlfn.CONCAT(AG96," years ",AH96," days") -> 4 years 146 days | AG96: 4 | AH96: 146 | AI96: 200000 | AJ96: 200000 | AK96: 2025 | AL96: 0
A97: IN01 | B97: 1101404553 | D97: 1101400923 | E97: 1 | F97: Factory Equipment & Tools | G97: 9007 | H97: 9007000008 | I97: Utility | J97: 1202010217 | K97: COOLING WATER SEC. PRO. PUMP-01 TO 06, CHILLING WATER SEC. PRO. PUMP-01 TO 07, PHE PRIMERY PROCESS PUMP-01 TO 03, CHILLER PRIMERY PROCESS PUMP-01 TO 03, TPAC/SIL/COOLING TOWER-02 & 03, PHE -01 TO 03 (ALFA LAVEL) | L97: B/NO : GST/356/21-22 DT.17.01.22 OF SCALE GU-103 | M97: ARD BOOKED FOR PURGRUNDFOS PUMP VIDE TSGO/21-22/ | O97: 1 | P97: EA | Q97: X | S97: 44910 | T97: 44910 | Y97: 2022 | Z97: 7877130.2 | AA97: 01 | AB97: ZSLM | AC97: 3650 | AD97: 10 | AE97: 0 | AF97: =_xlfn.CONCAT(AG97," years ",AH97," days") -> 2 years 18 days | AG97: 2 | AH97: 18 | AI97: 7877130.2 | AJ97: 1614272 | AK97: 2025 | AL97: 390619.48
A98: IN01 | B98: 1101404680 | D98: 1101400923 | E98: 2 | F98: Factory Equipment & Tools | G98: 9007 | H98: 9007000008 | I98: Utility | J98: 1202010217 | K98: Clloing Tower Pipe Line | L98: SS SEAMLESS ,SS ERW,PPR PIPE & FITTINGS INC-104 | M98: LUDING INSULATION (All Pipe Lines)(Addition to N | O98: 1 | P98: EA | Q98: X | S98: 45000 | T98: 45000 | Y98: 2023 | Z98: 4196003.7 | AA98: 01 | AB98: ZSLM | AC98: 3650 | AD98: 10 | AE98: 0 | AF98: =_xlfn.CONCAT(AG98," years ",AH98," days") -> 1 years 293 days | AG98: 1 | AH98: 293 | AI98: 4196003.7 | AJ98: 756430 | AK98: 2025 | AL98: 208076.06
A99: IN01 | B99: 1101405165 | D99: 1101400923 | E99: 3 | F99: Factory Equipment & Tools | G99: 9007 | H99: 9007000008 | I99: Utility | J99: 1202010217 | K99: CHILLER Primary Pump 1 | L99: B/NO. EPL/2023-24/167 DTD: 30.03.24 OF ENERP-105 | M99: RONE BOOKED FOR PUR 15 KW CHILLER PUMP VIDE TSGO | O99: 4 | P99: EA | Q99: X | S99: 45402 | T99: 45402 | Y99: 2024 | Z99: 668360 | AA99: 01 | AB99: ZSLM | AC99: 3650 | AD99: 10 | AE99: 0 | AF99: =_xlfn.CONCAT(AG99," years ",AH99," days") -> 0 years 256 days | AG99: 0 | AH99: 256 | AI99: 668360 | AJ99: 46877 | AK99: 2025 | AL99: 33143.088
A100: IN01 | B100: 1101100498 | D100: 1101400923 | E100: 4 | F100: Factory Equipment & Tools | G100: 9007 | H100: 9007000008 | I100: Utility | J100: 1202010217 | L100: Cooling Tower-106 | O100: 1 | P100: EA | Q100: X | S100: 40446 | T100: 43340 | Y100: 2018 | Z100: 210000 | AA100: 01 | AB100: ZSLM | AC100: 2592 | AD100: 7 | AE100: 1 | AF100: =_xlfn.CONCAT(AG100," years ",AH100," days") -> 6 years 128 days | AG100: 6 | AH100: 128 | AI100: 210000 | AJ100: 187720 | AK100: 2025 | AL100: 14664.259
A101: IN01 | B101: 1101504332 | D101: 1101400923 | E101: 5 | F101: Factory Equipment & Tools | G101: 9007 | H101: 9007000008 | I101: Utility | J101: 1202010217 | L101: Grundfos Chilled water Pump for Cooling Towe-107 | M101: r Model no NB-50-200/181 | O101: 1 | P101: EA | Q101: X | S101: 41940 | T101: 43340 | Y101: 2018 | Z101: 110000 | AA101: 01 | AB101: ZSLM | AC101: 2227 | AD101: 6 | AE101: 1 | AF101: =_xlfn.CONCAT(AG101," years ",AH101," days") -> 6 years 37 days | AG101: 6 | AH101: 37 | AI101: 110000 | AJ101: 110000 | AK101: 2025 | AL101: 0
A102: IN01 | B102: 1101504335 | D102: 1101400923 | E102: 6 | F102: Factory Equipment & Tools | G102: 9007 | H102: 9007000008 | I102: Utility | J102: 1202010217 | L102: Supply of Grundfos Make Pump Model no NB 40--108 | M102: 160/144 | O102: 1 | P102: EA | Q102: X | S102: 41944 | T102: 43340 | Y102: 2018 | Z102: 57500 | AA102: 01 | AB102: ZSLM | AC102: 2227 | AD102: 6 | AE102: 1 | AF102: =_xlfn.CONCAT(AG102," years ",AH102," days") -> 6 years 37 days | AG102: 6 | AH102: 37 | AI102: 57500 | AJ102: 57500 | AK102: 2025 | AL102: 0
A103: IN01 | B103: 1101403333 | E103: 0 | F103: Factory Equipment & Tools | G103: 9007 | H103: 9007000009 | I103: Utility | J103: 1202010217 | K103: TPAC/SIL/HPAD-001 | L103: Being Compressed air dryer high pressure 300-110 | M103: cfm 40 to 42 bar G . Air dryer cooled . R134A p | O103: 1 | P103: EA | Q103: X | S103: 44020 | T103: 44020 | Y103: 2020 | Z103: 232250 | AA103: 01 | AB103: ZSLM | AC103: 3650 | AD103: 10 | AE103: 0 | AF103: =_xlfn.CONCAT(AG103," years ",AH103," days") -> 4 years 178 days | AG103: 4 | AH103: 178 | AI103: 232250 | AJ103: 104226 | AK103: 2025 | AL103: 11517.219
A104: IN01 | B104: 1101404036 | D104: 1101403333 | E104: 1 | F104: Factory Equipment & Tools | G104: 9007 | H104: 9007000009 | I104: Utility | J104: 1202010217 | K104: TPAC/SIL/HP-001 | L104: Being COMPRESSOR BLOCK-P10(LOCAL P/R) pur fr-111 | M104: om Chicago Pneumatic Compressors vide inv no FO2 | O104: 1 | P104: EA | Q104: X | S104: 44621 | T104: 44621 | Y104: 2022 | Z104: 1622288 | AA104: 01 | AB104: ZSLM | AC104: 3650 | AD104: 10 | AE104: 0 | AF104: =_xlfn.CONCAT(AG104," years ",AH104," days") -> 2 years 307 days | AG104: 2 | AH104: 307 | AI104: 1622288 | AJ104: 460908 | AK104: 2025 | AL104: 80447.283
A105: IN01 | B105: 1101405073 | D105: 1101403333 | E105: 2 | F105: Factory Equipment & Tools | G105: 9007 | H105: 9007000009 | I105: Utility | J105: 1202010217 | L105: BEING T/F THROUGH J/V AGST B/NO. 070 DT: 18.-112 | M105: 01.24 OF GRACE ENGINEERING WORKS BOOKED FOR CHIL | O105: 1 | P105: EA | Q105: X | S105: 45310 | T105: 45310 | Y105: 2024 | Z105: 48353 | AA105: 01 | AB105: ZSLM | AC105: 3650 | AD105: 10 | AE105: 0 | AF105: =_xlfn.CONCAT(AG105," years ",AH105," days") -> 0 years 348 days | AG105: 0 | AH105: 348 | AI105: 48353 | AJ105: 4610 | AK105: 2025 | AL105: 2397.8732
A106: IN01 | B106: 1101400374 | E106: 0 | F106: Factory Equipment & Tools | G106: 9007 | H106: 9007000010 | I106: Utility | J106: 1202010217 | K106: TPAC/SIL/HP-002 & HPAD 2 | L106: Air Compressor-Chicago Phenu-114 | O106: 1 | P106: EA | Q106: X | S106: 40089 | T106: 43340 | Y106: 2018 | Z106: 380000 | AA106: 01 | AB106: ZSLM | AC106: 402 | AD106: 1 | AE106: 1 | AF106: =_xlfn.CONCAT(AG106," years ",AH106," days") -> 1 years 37 days | AG106: 1 | AH106: 37 | AI106: 380000 | AJ106: 380000 | AK106: 2025 | AL106: 0
A107: IN01 | B107: 1101400525 | E107: 0 | F107: Factory Equipment & Tools | G107: 9007 | H107: 9007000011 | I107: Utility | J107: 1202010217 | K107: TPAC/SIL/HP-003 & HPAD 3 | L107: Oil Free Air Pet Compressor-Big-116 | O107: 1 | P107: EA | Q107: X | S107: 40492 | T107: 43340 | Y107: 2018 | Z107: 640000 | AA107: 01 | AB107: ZSLM | AC107: 803 | AD107: 2 | AE107: 2 | AF107: =_xlfn.CONCAT(AG107," years ",AH107," days") -> 2 years 73 days | AG107: 2 | AH107: 73 | AI107: 640000 | AJ107: 640000 | AK107: 2025 | AL107: 0
A108: IN01 | B108: 1101400613 | E108: 0 | F108: Factory Equipment & Tools | G108: 9007 | H108: 9007000012 | I108: Utility | J108: 1202010217 | K108: TPAC/SIL/HP-004 | L108: Oil Free Air Pet Compressor-118 | O108: 1 | P108: EA | Q108: X | S108: 40679 | T108: 43340 | Y108: 2018 | Z108: 660000 | AA108: 01 | AB108: ZSLM | AC108: 986 | AD108: 2 | AE108: 9 | AF108: =_xlfn.CONCAT(AG108," years ",AH108," days") -> 2 years 256 days | AG108: 2 | AH108: 256 | AI108: 660000 | AJ108: 660000 | AK108: 2025 | AL108: 0
A109: IN01 | B109: 1101403697 | D109: 1101400613 | E109: 1 | F109: Factory Equipment & Tools | G109: 9007 | H109: 9007000012 | I109: Utility | J109: 1202010217 | K109: TPAC/SIL/HPAD-004 | L109: Being Compressed air dryer high pressure 300-119 | M109: cfm 40 to 42 bar G air cooled R134A pur from Gem | O109: 1 | P109: EA | Q109: X | S109: 44336 | T109: 44336 | Y109: 2021 | Z109: 164664 | AA109: 01 | AB109: ZSLM | AC109: 3650 | AD109: 10 | AE109: 0 | AF109: =_xlfn.CONCAT(AG109," years ",AH109," days") -> 3 years 227 days | AG109: 3 | AH109: 227 | AI109: 164664 | AJ109: 59640 | AK109: 2025 | AL109: 8165.4773
A110: IN01 | B110: 1101404755 | D110: 1101400613 | E110: 2 | F110: Factory Equipment & Tools | G110: 9007 | H110: 9007000012 | I110: Utility | J110: 1202010217 | L110: BEING T/F THROUGH J/V AGST B/NO. T/23-24/015-120 | M110: DT: 09.05.23 OF PACE AFTERMARKET BOOKED FOR PUR | O110: 4 | P110: EA | Q110: X | S110: 45064 | T110: 45064 | Y110: 2023 | Z110: 247080 | AA110: 01 | AB110: ZSLM | AC110: 3650 | AD110: 10 | AE110: 0 | AF110: =_xlfn.CONCAT(AG110," years ",AH110," days") -> 1 years 229 days | AG110: 1 | AH110: 229 | AI110: 247080 | AJ110: 40210 | AK110: 2025 | AL110: 12252.192
A111: IN01 | B111: 1101404799 | D111: 1101400613 | E111: 3 | F111: Factory Equipment & Tools | G111: 9007 | H111: 9007000012 | I111: Utility | J111: 1202010217 | L111: B/NO. 031 DT: 15.06.23 OF GRACE ENGINEERING -121 | M111: BOOKED FOR AIRLINE MAKING FOR NEW MOULD ROOM IN | O111: 1 | P111: EA | Q111: X | S111: 45108 | T111: 45108 | Y111: 2023 | Z111: 56781 | AA111: 01 | AB111: ZSLM | AC111: 3650 | AD111: 10 | AE111: 0 | AF111: =_xlfn.CONCAT(AG111," years ",AH111," days") -> 1 years 185 days | AG111: 1 | AH111: 185 | AI111: 56781 | AJ111: 8556 | AK111: 2025 | AL111: 2815.7564
A112: IN01 | B112: 1101504320 | E112: 0 | F112: Factory Equipment & Tools | G112: 9007 | H112: 9007000013 | I112: Utility | J112: 1202010217 | K112: TPAC/SIL/HP-005, TPAC/SIL/HPAD-005 | L112: Compressor AIR DRYER-123 | O112: 1 | P112: EA | Q112: X | S112: 41365 | T112: 43340 | Y112: 2018 | Z112: 390000 | AA112: 01 | AB112: ZSLM | AC112: 3504 | AD112: 9 | AE112: 7 | AF112: =_xlfn.CONCAT(AG112," years ",AH112," days") -> 6 years 128 days | AG112: 6 | AH112: 128 | AI112: 390000 | AJ112: 257885 | AK112: 2025 | AL112: 20145.822
A113: IN01 | B113: 1101404871 | D113: 1101504320 | E113: 1 | F113: Factory Equipment & Tools | G113: 9007 | H113: 9007000013 | I113: Utility | J113: 1202010217 | L113: BEING T/F THROUGH J/V AGST B/NO. 23-324/2981-124 | M113: DT: 18.08.23 OF SAINATH STRUCTURES BOOKED FOR P | O113: 401 | P113: EA | Q113: X | S113: 45167 | T113: 45167 | Y113: 2023 | Z113: 24149.5 | AA113: 01 | AB113: ZSLM | AC113: 3650 | AD113: 10 | AE113: 0 | AF113: =_xlfn.CONCAT(AG113," years ",AH113," days") -> 1 years 126 days | AG113: 1 | AH113: 126 | AI113: 24149.5 | AJ113: 3249 | AK113: 2025 | AL113: 1197.1545
A114: IN01 | B114: 1101504267 | E114: 0 | F114: Factory Equipment & Tools | G114: 9007 | H114: 9007000014 | I114: Utility | J114: 1202010217 | K114: TPAC/SIL/HP-006, TPAC/SIL/HPAD-006 | L114: CP AIR COMPRESSOR with all Accessories-126 | O114: 1 | P114: EA | Q114: X | S114: 40089 | T114: 43340 | Y114: 2018 | Z114: 410000 | AA114: 01 | AB114: ZSLM | AC114: 402 | AD114: 1 | AE114: 1 | AF114: =_xlfn.CONCAT(AG114," years ",AH114," days") -> 1 years 37 days | AG114: 1 | AH114: 37 | AI114: 410000 | AJ114: 410000 | AK114: 2025 | AL114: 0
A115: IN01 | B115: 1101504330 | D115: 1101504267 | E115: 1 | F115: Factory Equipment & Tools | G115: 9007 | H115: 9007000014 | I115: Utility | J115: 1202010217 | L115: Second Stage InterCooter for HP Compressor s-127 | M115: ingle stage | O115: 1 | P115: EA | Q115: X | S115: 42490 | T115: 43340 | Y115: 2018 | Z115: 135000 | AA115: 01 | AB115: ZSLM | AC115: 2774 | AD115: 7 | AE115: 7 | AF115: =_xlfn.CONCAT(AG115," years ",AH115," days") -> 6 years 128 days | AG115: 6 | AH115: 128 | AI115: 135000 | AJ115: 112760 | AK115: 2025 | AL115: 8808.1327
A116: IN01 | B116: 1101402671 | E116: 0 | F116: Factory Equipment & Tools | G116: 9007 | H116: 9007000015 | I116: Utility | J116: 1202010217 | K116: TPAC/SIL/LP-001, TPAC/SIL/LPAD-001 | L116: LP AIR COMPRESSOR -129 | O116: 1 | P116: EA | Q116: X | S116: 43346 | T116: 43346 | Y116: 2018 | Z116: 2516472 | AA116: 01 | AB116: ZSLM | AC116: 3650 | AD116: 10 | AE116: 0 | AF116: =_xlfn.CONCAT(AG116," years ",AH116," days") -> 6 years 122 days | AG116: 6 | AH116: 122 | AI116: 2516472 | AJ116: 1593306 | AK116: 2025 | AL116: 124789.4
A117: IN01 | B117: 1101100979 | D117: 1101402671 | E117: 1 | F117: Factory Equipment & Tools | G117: 9007 | H117: 9007000015 | I117: Utility | J117: 1202010217 | L117: AIR DRYER -130 | O117: 1 | P117: EA | Q117: X | S117: 41365 | T117: 43340 | Y117: 2018 | Z117: 300000 | AA117: 01 | AB117: ZSLM | AC117: 3504 | AD117: 9 | AE117: 7 | AF117: =_xlfn.CONCAT(AG117," years ",AH117," days") -> 6 years 128 days | AG117: 6 | AH117: 128 | AI117: 300000 | AJ117: 198373 | AK117: 2025 | AL117: 15496.863
A118: IN01 | B118: 1101402942 | E118: 0 | F118: Factory Equipment & Tools | G118: 9007 | H118: 9007000016 | I118: Utility | J118: 1202010217 | K118: TPAC/SIL/LP-002 & TPAC/SIL/LPAD-002 | L118: BEING LP AIR COMPRESSOR & GI HOT DIP PLATE F-132 | M118: OR COMPRESSOR CAPITALIZED VIDE PUR FROM KAESER O | O118: 1 | P118: EA | Q118: X | S118: 43577 | T118: 43577 | Y118: 2019 | Z118: 2511704 | AA118: 01 | AB118: ZSLM | AC118: 3650 | AD118: 10 | AE118: 0 | AF118: =_xlfn.CONCAT(AG118," years ",AH118," days") -> 5 years 256 days | AG118: 5 | AH118: 256 | AI118: 2511704 | AJ118: 1432015 | AK118: 2025 | AL118: 124553.34
A119: IN01 | B119: 1101402943 | D119: 1101402942 | E119: 1 | F119: Factory Equipment & Tools | G119: 9007 | H119: 9007000016 | I119: Utility | J119: 1202010217 | L119: BEING COPPER FLEXIBLE CABLE AND WALKER ALLOY-133 | M119: HIGH PREASURE FILTER CAPITALISED PUR FROM GANES | O119: 1 | P119: EA | Q119: X | S119: 43577 | T119: 43577 | Y119: 2019 | Z119: 114300 | AA119: 01 | AB119: ZSLM | AC119: 3650 | AD119: 10 | AE119: 0 | AF119: =_xlfn.CONCAT(AG119," years ",AH119," days") -> 5 years 256 days | AG119: 5 | AH119: 256 | AI119: 114300 | AJ119: 65167 | AK119: 2025 | AL119: 5667.6849
A120: IN01 | B120: 1101404035 | E120: 0 | F120: Factory Equipment & Tools | G120: 9007 | H120: 9007000017 | I120: Utility | J120: 1202010217 | K120: TPAC/SIL/LP-003. TPAC/SIL/LPAD-003 | L120: Being Sullair make screw air compressor Mode-135 | M120: l:AS75 12 vsd pur from Yashashwi Pumps & Compres | O120: 1 | P120: EA | Q120: X | S120: 44621 | T120: 44621 | Y120: 2022 | Z120: 1885954 | AA120: 01 | AB120: ZSLM | AC120: 3650 | AD120: 10 | AE120: 0 | AF120: =_xlfn.CONCAT(AG120," years ",AH120," days") -> 2 years 307 days | AG120: 2 | AH120: 307 | AI120: 1885954 | AJ120: 535818 | AK120: 2025 | AL120: 93522.266
A121: IN01 | B121: 1101404848 | D121: 1101404035 | E121: 1 | F121: Factory Equipment & Tools | G121: 9007 | H121: 9007000017 | I121: Utility | J121: 1202010217 | L121: BEING T/F THROUGH J/V AGST B/NO. 00805 DT: 0-136 | M121: 3.08.23 OF GANESH ELE BOOKED FOR PUR PRESSURE SW | O121: 1 | P121: EA | Q121: X | S121: 45148 | T121: 45148 | Y121: 2023 | Z121: 15725 | AA121: 01 | AB121: ZSLM | AC121: 3650 | AD121: 10 | AE121: 0 | AF121: =_xlfn.CONCAT(AG121," years ",AH121," days") -> 1 years 145 days | AG121: 1 | AH121: 145 | AI121: 15725 | AJ121: 2197 | AK121: 2025 | AL121: 779.97945
A122: IN01 | B122: 1101404550 | E122: 0 | F122: Factory Equipment & Tools | G122: 9007 | H122: 9007000018 | I122: Utility | J122: 1202010217 | K122: TPAC/SIL/LP-004 & 005 , TPAC/SIL/LPAD-004, 005 | L122: T/F THROUGH J/V AGTS B/NO. PI1000036532 DT: -138 | M122: 08.06.22 BOOKED FOR PUR LP AIR COMPRESSOR FOR NE | O122: 1 | P122: EA | Q122: X | S122: 44910 | T122: 44910 | Y122: 2022 | Z122: 7098917.5 | AA122: 01 | AB122: ZSLM | AC122: 3650 | AD122: 10 | AE122: 0 | AF122: =_xlfn.CONCAT(AG122," years ",AH122," days") -> 2 years 18 days | AG122: 2 | AH122: 18 | AI122: 7098917.5 | AJ122: 1454792 | AK122: 2025 | AL122: 352028.4
A123: IN01 | B123: 1101404554 | D123: 1101404550 | E123: 1 | F123: Factory Equipment & Tools | G123: 9007 | H123: 9007000018 | I123: Utility | J123: 1202010217 | K123: LP 04 & 05 | L123: B/NO. DOM/211 DT: 22.12.21 OF PRAKASH STEELA-139 | M123: GE BOOKED FOR PUR STAINLESS STEEL PIPE VIDE TSGO | O123: 1 | P123: EA | Q123: X | S123: 44910 | T123: 44910 | Y123: 2022 | Z123: 13700081 | AA123: 01 | AB123: ZSLM | AC123: 3650 | AD123: 10 | AE123: 0 | AF123: =_xlfn.CONCAT(AG123," years ",AH123," days") -> 2 years 18 days | AG123: 2 | AH123: 18 | AI123: 13700081 | AJ123: 2807578 | AK123: 2025 | AL123: 679374.22
...
